{
  "id": "azvFmffyuS4",
  "title": "Sonic Underground - Mindy's Sweet Sixteen!",
  "formats": [
    {
      "asr": 22050,
      "filesize": 4695385,
      "format_id": "139",
      "format_note": "low",
      "quality": 2,
      "tbr": 47.582,
      "url": "https://r3---sn-uxanug5-hxael.googlevideo.com/videoplayback?expire=1632689184&ei=wIdQYeDzFLCGssUPr6OzoAc&ip=137.147.137.77&id=o-ADuOP6mq-6W7_a9e4vMsdb3psW7QPFoFkQVP4lSE_97W&itag=139&source=youtube&requiressl=yes&mh=Pl&mm=31%2C29&mn=sn-uxanug5-hxael%2Csn-hxa7zn7s&ms=au%2Crdu&mv=m&mvi=3&pl=18&initcwndbps=1747500&vprv=1&mime=audio%2Fmp4&gir=yes&clen=4695385&dur=789.431&lmt=1533948770578792&mt=1632667252&fvip=3&keepalive=yes&fexp=24001373%2C24007246&c=ANDROID&sparams=expire%2Cei%2Cip%2Cid%2Citag%2Csource%2Crequiressl%2Cvprv%2Cmime%2Cgir%2Cclen%2Cdur%2Clmt&sig=AOq0QJ8wRQIgPIe-fCEsAXdXQpYEgVJ-9qcrVmczzMXnNQilJWkWumkCIQCex89G0Jw3qPmfjk5Z5w78WvMjesCP437VqEMou00uLw%3D%3D&lsparams=mh%2Cmm%2Cmn%2Cms%2Cmv%2Cmvi%2Cpl%2Cinitcwndbps&lsig=AG3C_xAwRAIgOosAFNtgc_RoT7D75iertCxahIVoulZtfVjtGykjsa0CICiBiSBFbkRxZpHej-re-H5-R2Xw9Jf1T6n0ok4Qxfno",
      "language": "",
      "language_preference": -1,
      "ext": "m4a",
      "vcodec": "none",
      "acodec": "mp4a.40.5",
      "abr": 47.582,
      "downloader_options": {
        "http_chunk_size": 10485760
      },
      "container": "m4a_dash",
      "protocol": "https",
      "audio_ext": "m4a",
      "video_ext": "none",
      "format": "139 - audio only (low)",
      "http_headers": {
        "User-Agent": "Mozilla/5.0 (Windows NT 10.0; Win64; x64) AppleWebKit/537.36 (KHTML, like Gecko) Chrome/69.0.3497.48 Safari/537.36",
        "Accept-Charset": "ISO-8859-1,utf-8;q=0.7,*;q=0.7",
        "Accept": "text/html,application/xhtml+xml,application/xml;q=0.9,*/*;q=0.8",
        "Accept-Encoding": "gzip, deflate",
        "Accept-Language": "en-us,en;q=0.5"
      }
    },
    {
      "asr": 48000,
      "filesize": 4775046,
      "format_id": "249",
      "format_note": "low",
      "quality": 2,
      "tbr": 48.397,
      "url": "https://r3---sn-uxanug5-hxael.googlevideo.com/videoplayback?expire=1632689184&ei=wIdQYeDzFLCGssUPr6OzoAc&ip=137.147.137.77&id=o-ADuOP6mq-6W7_a9e4vMsdb3psW7QPFoFkQVP4lSE_97W&itag=249&source=youtube&requiressl=yes&mh=Pl&mm=31%2C29&mn=sn-uxanug5-hxael%2Csn-hxa7zn7s&ms=au%2Crdu&mv=m&mvi=3&pl=18&initcwndbps=1747500&vprv=1&mime=audio%2Fwebm&gir=yes&clen=4775046&dur=789.301&lmt=1533951189606136&mt=1632667252&fvip=3&keepalive=yes&fexp=24001373%2C24007246&c=ANDROID&sparams=expire%2Cei%2Cip%2Cid%2Citag%2Csource%2Crequiressl%2Cvprv%2Cmime%2Cgir%2Cclen%2Cdur%2Clmt&sig=AOq0QJ8wRAIgQtrl0uUExaMk6b2ImK-GmYpgJerrSFUXpXUU87OxdJsCIGiWvfWfLvW_v10tvPxuRs1PzES_nb-WqWow63rNl8Hg&lsparams=mh%2Cmm%2Cmn%2Cms%2Cmv%2Cmvi%2Cpl%2Cinitcwndbps&lsig=AG3C_xAwRAIgOosAFNtgc_RoT7D75iertCxahIVoulZtfVjtGykjsa0CICiBiSBFbkRxZpHej-re-H5-R2Xw9Jf1T6n0ok4Qxfno",
      "language": "",
      "language_preference": -1,
      "ext": "webm",
      "vcodec": "none",
      "acodec": "opus",
      "abr": 48.397,
      "downloader_options": {
        "http_chunk_size": 10485760
      },
      "container": "webm_dash",
      "protocol": "https",
      "audio_ext": "webm",
      "video_ext": "none",
      "format": "249 - audio only (low)",
      "http_headers": {
        "User-Agent": "Mozilla/5.0 (Windows NT 10.0; Win64; x64) AppleWebKit/537.36 (KHTML, like Gecko) Chrome/69.0.3497.48 Safari/537.36",
        "Accept-Charset": "ISO-8859-1,utf-8;q=0.7,*;q=0.7",
        "Accept": "text/html,application/xhtml+xml,application/xml;q=0.9,*/*;q=0.8",
        "Accept-Encoding": "gzip, deflate",
        "Accept-Language": "en-us,en;q=0.5"
      }
    },
    {
      "asr": 48000,
      "filesize": 6091438,
      "format_id": "250",
      "format_note": "low",
      "quality": 2,
      "tbr": 61.74,
      "url": "https://r3---sn-uxanug5-hxael.googlevideo.com/videoplayback?expire=1632689184&ei=wIdQYeDzFLCGssUPr6OzoAc&ip=137.147.137.77&id=o-ADuOP6mq-6W7_a9e4vMsdb3psW7QPFoFkQVP4lSE_97W&itag=250&source=youtube&requiressl=yes&mh=Pl&mm=31%2C29&mn=sn-uxanug5-hxael%2Csn-hxa7zn7s&ms=au%2Crdu&mv=m&mvi=3&pl=18&initcwndbps=1747500&vprv=1&mime=audio%2Fwebm&gir=yes&clen=6091438&dur=789.301&lmt=1533951189925090&mt=1632667252&fvip=3&keepalive=yes&fexp=24001373%2C24007246&c=ANDROID&sparams=expire%2Cei%2Cip%2Cid%2Citag%2Csource%2Crequiressl%2Cvprv%2Cmime%2Cgir%2Cclen%2Cdur%2Clmt&sig=AOq0QJ8wRQIhAL0ApM8zEoRqGkUvK8A1SBRn-BzqUlXYY-nXSgvi1wy3AiAhMzyQAQT8FiJnxtPzrGqS5jVC7bfKxdNPotUP5ZwwZg%3D%3D&lsparams=mh%2Cmm%2Cmn%2Cms%2Cmv%2Cmvi%2Cpl%2Cinitcwndbps&lsig=AG3C_xAwRAIgOosAFNtgc_RoT7D75iertCxahIVoulZtfVjtGykjsa0CICiBiSBFbkRxZpHej-re-H5-R2Xw9Jf1T6n0ok4Qxfno",
      "language": "",
      "language_preference": -1,
      "ext": "webm",
      "vcodec": "none",
      "acodec": "opus",
      "abr": 61.74,
      "downloader_options": {
        "http_chunk_size": 10485760
      },
      "container": "webm_dash",
      "protocol": "https",
      "audio_ext": "webm",
      "video_ext": "none",
      "format": "250 - audio only (low)",
      "http_headers": {
        "User-Agent": "Mozilla/5.0 (Windows NT 10.0; Win64; x64) AppleWebKit/537.36 (KHTML, like Gecko) Chrome/69.0.3497.48 Safari/537.36",
        "Accept-Charset": "ISO-8859-1,utf-8;q=0.7,*;q=0.7",
        "Accept": "text/html,application/xhtml+xml,application/xml;q=0.9,*/*;q=0.8",
        "Accept-Encoding": "gzip, deflate",
        "Accept-Language": "en-us,en;q=0.5"
      }
    },
    {
      "asr": 44100,
      "filesize": 12537232,
      "format_id": "140",
      "format_note": "medium",
      "quality": 3,
      "tbr": 127.065,
      "url": "https://r3---sn-uxanug5-hxael.googlevideo.com/videoplayback?expire=1632689184&ei=wIdQYeDzFLCGssUPr6OzoAc&ip=137.147.137.77&id=o-ADuOP6mq-6W7_a9e4vMsdb3psW7QPFoFkQVP4lSE_97W&itag=140&source=youtube&requiressl=yes&mh=Pl&mm=31%2C29&mn=sn-uxanug5-hxael%2Csn-hxa7zn7s&ms=au%2Crdu&mv=m&mvi=3&pl=18&initcwndbps=1747500&vprv=1&mime=audio%2Fmp4&gir=yes&clen=12537232&dur=789.339&lmt=1533948771766373&mt=1632667252&fvip=3&keepalive=yes&fexp=24001373%2C24007246&c=ANDROID&sparams=expire%2Cei%2Cip%2Cid%2Citag%2Csource%2Crequiressl%2Cvprv%2Cmime%2Cgir%2Cclen%2Cdur%2Clmt&sig=AOq0QJ8wRQIgUWJhxEoJ5RCotYhaIWrc60R84VCKwulzYCilI_pXFIACIQCOadcZkpv_foj-twv0Y_4mG8KYBf3hBTBkhF-ivdTRSA%3D%3D&lsparams=mh%2Cmm%2Cmn%2Cms%2Cmv%2Cmvi%2Cpl%2Cinitcwndbps&lsig=AG3C_xAwRAIgOosAFNtgc_RoT7D75iertCxahIVoulZtfVjtGykjsa0CICiBiSBFbkRxZpHej-re-H5-R2Xw9Jf1T6n0ok4Qxfno",
      "language": "",
      "language_preference": -1,
      "ext": "m4a",
      "vcodec": "none",
      "acodec": "mp4a.40.2",
      "abr": 127.065,
      "downloader_options": {
        "http_chunk_size": 10485760
      },
      "container": "m4a_dash",
      "protocol": "https",
      "audio_ext": "m4a",
      "video_ext": "none",
      "format": "140 - audio only (medium)",
      "http_headers": {
        "User-Agent": "Mozilla/5.0 (Windows NT 10.0; Win64; x64) AppleWebKit/537.36 (KHTML, like Gecko) Chrome/69.0.3497.48 Safari/537.36",
        "Accept-Charset": "ISO-8859-1,utf-8;q=0.7,*;q=0.7",
        "Accept": "text/html,application/xhtml+xml,application/xml;q=0.9,*/*;q=0.8",
        "Accept-Encoding": "gzip, deflate",
        "Accept-Language": "en-us,en;q=0.5"
      }
    },
    {
      "asr": 48000,
      "filesize": 11581768,
      "format_id": "251",
      "format_note": "medium",
      "quality": 3,
      "tbr": 117.387,
      "url": "https://r3---sn-uxanug5-hxael.googlevideo.com/videoplayback?expire=1632689184&ei=wIdQYeDzFLCGssUPr6OzoAc&ip=137.147.137.77&id=o-ADuOP6mq-6W7_a9e4vMsdb3psW7QPFoFkQVP4lSE_97W&itag=251&source=youtube&requiressl=yes&mh=Pl&mm=31%2C29&mn=sn-uxanug5-hxael%2Csn-hxa7zn7s&ms=au%2Crdu&mv=m&mvi=3&pl=18&initcwndbps=1747500&vprv=1&mime=audio%2Fwebm&gir=yes&clen=11581768&dur=789.301&lmt=1533951190026244&mt=1632667252&fvip=3&keepalive=yes&fexp=24001373%2C24007246&c=ANDROID&sparams=expire%2Cei%2Cip%2Cid%2Citag%2Csource%2Crequiressl%2Cvprv%2Cmime%2Cgir%2Cclen%2Cdur%2Clmt&sig=AOq0QJ8wRQIgJGlZQ59ypeaZ1rsvZ4lMbmnrvWFTPav9VzLRB_GhgHACIQCN9p9SVPY-N475OQNJKr5GLKfqa8RiVNzBOPOiRSn1yQ%3D%3D&lsparams=mh%2Cmm%2Cmn%2Cms%2Cmv%2Cmvi%2Cpl%2Cinitcwndbps&lsig=AG3C_xAwRAIgOosAFNtgc_RoT7D75iertCxahIVoulZtfVjtGykjsa0CICiBiSBFbkRxZpHej-re-H5-R2Xw9Jf1T6n0ok4Qxfno",
      "language": "",
      "language_preference": -1,
      "ext": "webm",
      "vcodec": "none",
      "acodec": "opus",
      "abr": 117.387,
      "downloader_options": {
        "http_chunk_size": 10485760
      },
      "container": "webm_dash",
      "protocol": "https",
      "audio_ext": "webm",
      "video_ext": "none",
      "format": "251 - audio only (medium)",
      "http_headers": {
        "User-Agent": "Mozilla/5.0 (Windows NT 10.0; Win64; x64) AppleWebKit/537.36 (KHTML, like Gecko) Chrome/69.0.3497.48 Safari/537.36",
        "Accept-Charset": "ISO-8859-1,utf-8;q=0.7,*;q=0.7",
        "Accept": "text/html,application/xhtml+xml,application/xml;q=0.9,*/*;q=0.8",
        "Accept-Encoding": "gzip, deflate",
        "Accept-Language": "en-us,en;q=0.5"
      }
    },
    {
      "asr": 22050,
      "filesize": 7061317,
      "format_id": "17",
      "format_note": "144p",
      "fps": 10,
      "height": 144,
      "quality": 0,
      "tbr": 71.562,
      "url": "https://r3---sn-uxanug5-hxael.googlevideo.com/videoplayback?expire=1632689184&ei=wIdQYeDzFLCGssUPr6OzoAc&ip=137.147.137.77&id=o-ADuOP6mq-6W7_a9e4vMsdb3psW7QPFoFkQVP4lSE_97W&itag=17&source=youtube&requiressl=yes&mh=Pl&mm=31%2C29&mn=sn-uxanug5-hxael%2Csn-hxa7zn7s&ms=au%2Crdu&mv=m&mvi=3&pl=18&initcwndbps=1747500&vprv=1&mime=video%2F3gpp&gir=yes&clen=7061317&dur=789.385&lmt=1533947040780917&mt=1632667252&fvip=3&fexp=24001373%2C24007246&c=ANDROID&sparams=expire%2Cei%2Cip%2Cid%2Citag%2Csource%2Crequiressl%2Cvprv%2Cmime%2Cgir%2Cclen%2Cdur%2Clmt&sig=AOq0QJ8wRQIhAIjOVggLgR-isPu0E7cu73yGGlb6ttkM2bb5d37mfZcOAiBih-oORczee1ubKvt6j4hehMdyfM7unPUlohHyfPtcOw%3D%3D&lsparams=mh%2Cmm%2Cmn%2Cms%2Cmv%2Cmvi%2Cpl%2Cinitcwndbps&lsig=AG3C_xAwRAIgOosAFNtgc_RoT7D75iertCxahIVoulZtfVjtGykjsa0CICiBiSBFbkRxZpHej-re-H5-R2Xw9Jf1T6n0ok4Qxfno",
      "width": 176,
      "language": "",
      "language_preference": -1,
      "ext": "3gp",
      "vcodec": "mp4v.20.3",
      "acodec": "mp4a.40.2",
      "protocol": "https",
      "video_ext": "3gp",
      "audio_ext": "none",
      "vbr": 71.562,
      "abr": 0.0,
      "format": "17 - 176x144 (144p)",
      "http_headers": {
        "User-Agent": "Mozilla/5.0 (Windows NT 10.0; Win64; x64) AppleWebKit/537.36 (KHTML, like Gecko) Chrome/69.0.3497.48 Safari/537.36",
        "Accept-Charset": "ISO-8859-1,utf-8;q=0.7,*;q=0.7",
        "Accept": "text/html,application/xhtml+xml,application/xml;q=0.9,*/*;q=0.8",
        "Accept-Encoding": "gzip, deflate",
        "Accept-Language": "en-us,en;q=0.5"
      }
    },
    {
      "filesize": 3672234,
      "format_id": "160",
      "format_note": "144p",
      "fps": 30,
      "height": 144,
      "quality": 0,
      "tbr": 37.22,
      "url": "https://r3---sn-uxanug5-hxael.googlevideo.com/videoplayback?expire=1632689184&ei=wIdQYeDzFLCGssUPr6OzoAc&ip=137.147.137.77&id=o-ADuOP6mq-6W7_a9e4vMsdb3psW7QPFoFkQVP4lSE_97W&itag=160&source=youtube&requiressl=yes&mh=Pl&mm=31%2C29&mn=sn-uxanug5-hxael%2Csn-hxa7zn7s&ms=au%2Crdu&mv=m&mvi=3&pl=18&initcwndbps=1747500&vprv=1&mime=video%2Fmp4&gir=yes&clen=3672234&dur=789.288&lmt=1533948716952198&mt=1632667252&fvip=3&keepalive=yes&fexp=24001373%2C24007246&c=ANDROID&sparams=expire%2Cei%2Cip%2Cid%2Citag%2Csource%2Crequiressl%2Cvprv%2Cmime%2Cgir%2Cclen%2Cdur%2Clmt&sig=AOq0QJ8wRgIhANGljwDKjuiI8L4CYDjJnMbQkqTxgx1_Zv_l9tmfL9U4AiEAqUttE_PaXHD9PA7SlBzLBFV06WT4WA-hKq02ADFOMGo%3D&lsparams=mh%2Cmm%2Cmn%2Cms%2Cmv%2Cmvi%2Cpl%2Cinitcwndbps&lsig=AG3C_xAwRAIgOosAFNtgc_RoT7D75iertCxahIVoulZtfVjtGykjsa0CICiBiSBFbkRxZpHej-re-H5-R2Xw9Jf1T6n0ok4Qxfno",
      "width": 256,
      "language": "",
      "language_preference": -1,
      "ext": "mp4",
      "vcodec": "avc1.4d400c",
      "acodec": "none",
      "vbr": 37.22,
      "downloader_options": {
        "http_chunk_size": 10485760
      },
      "container": "mp4_dash",
      "protocol": "https",
      "video_ext": "mp4",
      "audio_ext": "none",
      "format": "160 - 256x144 (144p)",
      "http_headers": {
        "User-Agent": "Mozilla/5.0 (Windows NT 10.0; Win64; x64) AppleWebKit/537.36 (KHTML, like Gecko) Chrome/69.0.3497.48 Safari/537.36",
        "Accept-Charset": "ISO-8859-1,utf-8;q=0.7,*;q=0.7",
        "Accept": "text/html,application/xhtml+xml,application/xml;q=0.9,*/*;q=0.8",
        "Accept-Encoding": "gzip, deflate",
        "Accept-Language": "en-us,en;q=0.5"
      }
    },
    {
      "filesize": 5420205,
      "format_id": "278",
      "format_note": "144p",
      "fps": 30,
      "height": 144,
      "quality": 0,
      "tbr": 54.937,
      "url": "https://r3---sn-uxanug5-hxael.googlevideo.com/videoplayback?expire=1632689184&ei=wIdQYeDzFLCGssUPr6OzoAc&ip=137.147.137.77&id=o-ADuOP6mq-6W7_a9e4vMsdb3psW7QPFoFkQVP4lSE_97W&itag=278&source=youtube&requiressl=yes&mh=Pl&mm=31%2C29&mn=sn-uxanug5-hxael%2Csn-hxa7zn7s&ms=au%2Crdu&mv=m&mvi=3&pl=18&initcwndbps=1747500&vprv=1&mime=video%2Fwebm&gir=yes&clen=5420205&dur=789.288&lmt=1533949525843067&mt=1632667252&fvip=3&keepalive=yes&fexp=24001373%2C24007246&c=ANDROID&sparams=expire%2Cei%2Cip%2Cid%2Citag%2Csource%2Crequiressl%2Cvprv%2Cmime%2Cgir%2Cclen%2Cdur%2Clmt&sig=AOq0QJ8wRQIgU74Qx-4htBLbxbUgWPsk8KMF535HmeyGsfC0c5qKheICIQDwMEwtfikOviP5-dLadeW5bRN0gmuDqLp38gz-NCN_tw%3D%3D&lsparams=mh%2Cmm%2Cmn%2Cms%2Cmv%2Cmvi%2Cpl%2Cinitcwndbps&lsig=AG3C_xAwRAIgOosAFNtgc_RoT7D75iertCxahIVoulZtfVjtGykjsa0CICiBiSBFbkRxZpHej-re-H5-R2Xw9Jf1T6n0ok4Qxfno",
      "width": 256,
      "language": "",
      "language_preference": -1,
      "ext": "webm",
      "vcodec": "vp9",
      "acodec": "none",
      "vbr": 54.937,
      "downloader_options": {
        "http_chunk_size": 10485760
      },
      "container": "webm_dash",
      "protocol": "https",
      "video_ext": "webm",
      "audio_ext": "none",
      "format": "278 - 256x144 (144p)",
      "http_headers": {
        "User-Agent": "Mozilla/5.0 (Windows NT 10.0; Win64; x64) AppleWebKit/537.36 (KHTML, like Gecko) Chrome/69.0.3497.48 Safari/537.36",
        "Accept-Charset": "ISO-8859-1,utf-8;q=0.7,*;q=0.7",
        "Accept": "text/html,application/xhtml+xml,application/xml;q=0.9,*/*;q=0.8",
        "Accept-Encoding": "gzip, deflate",
        "Accept-Language": "en-us,en;q=0.5"
      }
    },
    {
      "filesize": 6112564,
      "format_id": "133",
      "format_note": "240p",
      "fps": 30,
      "height": 240,
      "quality": 5,
      "tbr": 61.955,
      "url": "https://r3---sn-uxanug5-hxael.googlevideo.com/videoplayback?expire=1632689184&ei=wIdQYeDzFLCGssUPr6OzoAc&ip=137.147.137.77&id=o-ADuOP6mq-6W7_a9e4vMsdb3psW7QPFoFkQVP4lSE_97W&itag=133&source=youtube&requiressl=yes&mh=Pl&mm=31%2C29&mn=sn-uxanug5-hxael%2Csn-hxa7zn7s&ms=au%2Crdu&mv=m&mvi=3&pl=18&initcwndbps=1747500&vprv=1&mime=video%2Fmp4&gir=yes&clen=6112564&dur=789.288&lmt=1533948717118798&mt=1632667252&fvip=3&keepalive=yes&fexp=24001373%2C24007246&c=ANDROID&sparams=expire%2Cei%2Cip%2Cid%2Citag%2Csource%2Crequiressl%2Cvprv%2Cmime%2Cgir%2Cclen%2Cdur%2Clmt&sig=AOq0QJ8wRAIgFhbCrK35ACmT_8Aix397p_Ki1JdrT-ZvCdtZUXN6J4kCIGTkOzqncVfpEY6YMBfjXXHUuecCl_egnnLRMOEvVn6O&lsparams=mh%2Cmm%2Cmn%2Cms%2Cmv%2Cmvi%2Cpl%2Cinitcwndbps&lsig=AG3C_xAwRAIgOosAFNtgc_RoT7D75iertCxahIVoulZtfVjtGykjsa0CICiBiSBFbkRxZpHej-re-H5-R2Xw9Jf1T6n0ok4Qxfno",
      "width": 426,
      "language": "",
      "language_preference": -1,
      "ext": "mp4",
      "vcodec": "avc1.4d4015",
      "acodec": "none",
      "vbr": 61.955,
      "downloader_options": {
        "http_chunk_size": 10485760
      },
      "container": "mp4_dash",
      "protocol": "https",
      "video_ext": "mp4",
      "audio_ext": "none",
      "format": "133 - 426x240 (240p)",
      "http_headers": {
        "User-Agent": "Mozilla/5.0 (Windows NT 10.0; Win64; x64) AppleWebKit/537.36 (KHTML, like Gecko) Chrome/69.0.3497.48 Safari/537.36",
        "Accept-Charset": "ISO-8859-1,utf-8;q=0.7,*;q=0.7",
        "Accept": "text/html,application/xhtml+xml,application/xml;q=0.9,*/*;q=0.8",
        "Accept-Encoding": "gzip, deflate",
        "Accept-Language": "en-us,en;q=0.5"
      }
    },
    {
      "filesize": 9525310,
      "format_id": "242",
      "format_note": "240p",
      "fps": 30,
      "height": 240,
      "quality": 5,
      "tbr": 96.545,
      "url": "https://r3---sn-uxanug5-hxael.googlevideo.com/videoplayback?expire=1632689184&ei=wIdQYeDzFLCGssUPr6OzoAc&ip=137.147.137.77&id=o-ADuOP6mq-6W7_a9e4vMsdb3psW7QPFoFkQVP4lSE_97W&itag=242&source=youtube&requiressl=yes&mh=Pl&mm=31%2C29&mn=sn-uxanug5-hxael%2Csn-hxa7zn7s&ms=au%2Crdu&mv=m&mvi=3&pl=18&initcwndbps=1747500&vprv=1&mime=video%2Fwebm&gir=yes&clen=9525310&dur=789.288&lmt=1533949525874968&mt=1632667252&fvip=3&keepalive=yes&fexp=24001373%2C24007246&c=ANDROID&sparams=expire%2Cei%2Cip%2Cid%2Citag%2Csource%2Crequiressl%2Cvprv%2Cmime%2Cgir%2Cclen%2Cdur%2Clmt&sig=AOq0QJ8wRQIhALB7gdvAzsha-QaZ1z3ecjn94bRD3H6oa2HBG2oITc3jAiBZuPXKogjisrrs6jVDY00NWGo5bBblKqlzUkXiMdD50A%3D%3D&lsparams=mh%2Cmm%2Cmn%2Cms%2Cmv%2Cmvi%2Cpl%2Cinitcwndbps&lsig=AG3C_xAwRAIgOosAFNtgc_RoT7D75iertCxahIVoulZtfVjtGykjsa0CICiBiSBFbkRxZpHej-re-H5-R2Xw9Jf1T6n0ok4Qxfno",
      "width": 426,
      "language": "",
      "language_preference": -1,
      "ext": "webm",
      "vcodec": "vp9",
      "acodec": "none",
      "vbr": 96.545,
      "downloader_options": {
        "http_chunk_size": 10485760
      },
      "container": "webm_dash",
      "protocol": "https",
      "video_ext": "webm",
      "audio_ext": "none",
      "format": "242 - 426x240 (240p)",
      "http_headers": {
        "User-Agent": "Mozilla/5.0 (Windows NT 10.0; Win64; x64) AppleWebKit/537.36 (KHTML, like Gecko) Chrome/69.0.3497.48 Safari/537.36",
        "Accept-Charset": "ISO-8859-1,utf-8;q=0.7,*;q=0.7",
        "Accept": "text/html,application/xhtml+xml,application/xml;q=0.9,*/*;q=0.8",
        "Accept-Encoding": "gzip, deflate",
        "Accept-Language": "en-us,en;q=0.5"
      }
    },
    {
      "filesize": 12145859,
      "format_id": "134",
      "format_note": "360p",
      "fps": 30,
      "height": 360,
      "quality": 6,
      "tbr": 123.106,
      "url": "https://r3---sn-uxanug5-hxael.googlevideo.com/videoplayback?expire=1632689184&ei=wIdQYeDzFLCGssUPr6OzoAc&ip=137.147.137.77&id=o-ADuOP6mq-6W7_a9e4vMsdb3psW7QPFoFkQVP4lSE_97W&itag=134&source=youtube&requiressl=yes&mh=Pl&mm=31%2C29&mn=sn-uxanug5-hxael%2Csn-hxa7zn7s&ms=au%2Crdu&mv=m&mvi=3&pl=18&initcwndbps=1747500&vprv=1&mime=video%2Fmp4&gir=yes&clen=12145859&dur=789.288&lmt=1533948717124086&mt=1632667252&fvip=3&keepalive=yes&fexp=24001373%2C24007246&c=ANDROID&sparams=expire%2Cei%2Cip%2Cid%2Citag%2Csource%2Crequiressl%2Cvprv%2Cmime%2Cgir%2Cclen%2Cdur%2Clmt&sig=AOq0QJ8wRQIgaG_ejI4HiUQtGmzdDZvMHXchG1Op1mvh5SySInnYy4QCIQD-43K2kolPZXjCtZQQcX_ChhPlq9ZAmOIZq4HpXdnwpg%3D%3D&lsparams=mh%2Cmm%2Cmn%2Cms%2Cmv%2Cmvi%2Cpl%2Cinitcwndbps&lsig=AG3C_xAwRAIgOosAFNtgc_RoT7D75iertCxahIVoulZtfVjtGykjsa0CICiBiSBFbkRxZpHej-re-H5-R2Xw9Jf1T6n0ok4Qxfno",
      "width": 640,
      "language": "",
      "language_preference": -1,
      "ext": "mp4",
      "vcodec": "avc1.4d401e",
      "acodec": "none",
      "vbr": 123.106,
      "downloader_options": {
        "http_chunk_size": 10485760
      },
      "container": "mp4_dash",
      "protocol": "https",
      "video_ext": "mp4",
      "audio_ext": "none",
      "format": "134 - 640x360 (360p)",
      "http_headers": {
        "User-Agent": "Mozilla/5.0 (Windows NT 10.0; Win64; x64) AppleWebKit/537.36 (KHTML, like Gecko) Chrome/69.0.3497.48 Safari/537.36",
        "Accept-Charset": "ISO-8859-1,utf-8;q=0.7,*;q=0.7",
        "Accept": "text/html,application/xhtml+xml,application/xml;q=0.9,*/*;q=0.8",
        "Accept-Encoding": "gzip, deflate",
        "Accept-Language": "en-us,en;q=0.5"
      }
    },
    {
      "asr": 44100,
      "filesize": 41368888,
      "format_id": "18",
      "format_note": "360p",
      "fps": 30,
      "height": 360,
      "quality": 6,
      "tbr": 419.276,
      "url": "https://r3---sn-uxanug5-hxael.googlevideo.com/videoplayback?expire=1632689184&ei=wIdQYeDzFLCGssUPr6OzoAc&ip=137.147.137.77&id=o-ADuOP6mq-6W7_a9e4vMsdb3psW7QPFoFkQVP4lSE_97W&itag=18&source=youtube&requiressl=yes&mh=Pl&mm=31%2C29&mn=sn-uxanug5-hxael%2Csn-hxa7zn7s&ms=au%2Crdu&mv=m&mvi=3&pl=18&initcwndbps=1747500&vprv=1&mime=video%2Fmp4&gir=yes&clen=41368888&ratebypass=yes&dur=789.339&lmt=1533948932593718&mt=1632667252&fvip=3&fexp=24001373%2C24007246&c=ANDROID&sparams=expire%2Cei%2Cip%2Cid%2Citag%2Csource%2Crequiressl%2Cvprv%2Cmime%2Cgir%2Cclen%2Cratebypass%2Cdur%2Clmt&sig=AOq0QJ8wRgIhAL8An04Y1jMVSiHiCSkD82xDNl3-QLUeWx6WGPtXGVgjAiEA4aaP2nEp5VHjxf41N_0gXKLmnCBt616wR6_FYQltd-Q%3D&lsparams=mh%2Cmm%2Cmn%2Cms%2Cmv%2Cmvi%2Cpl%2Cinitcwndbps&lsig=AG3C_xAwRAIgOosAFNtgc_RoT7D75iertCxahIVoulZtfVjtGykjsa0CICiBiSBFbkRxZpHej-re-H5-R2Xw9Jf1T6n0ok4Qxfno",
      "width": 640,
      "language": "",
      "language_preference": -1,
      "ext": "mp4",
      "vcodec": "avc1.42001E",
      "acodec": "mp4a.40.2",
      "protocol": "https",
      "video_ext": "mp4",
      "audio_ext": "none",
      "vbr": 419.276,
      "abr": 0.0,
      "format": "18 - 640x360 (360p)",
      "http_headers": {
        "User-Agent": "Mozilla/5.0 (Windows NT 10.0; Win64; x64) AppleWebKit/537.36 (KHTML, like Gecko) Chrome/69.0.3497.48 Safari/537.36",
        "Accept-Charset": "ISO-8859-1,utf-8;q=0.7,*;q=0.7",
        "Accept": "text/html,application/xhtml+xml,application/xml;q=0.9,*/*;q=0.8",
        "Accept-Encoding": "gzip, deflate",
        "Accept-Language": "en-us,en;q=0.5"
      }
    },
    {
      "filesize": 15976634,
      "format_id": "243",
      "format_note": "360p",
      "fps": 30,
      "height": 360,
      "quality": 6,
      "tbr": 161.934,
      "url": "https://r3---sn-uxanug5-hxael.googlevideo.com/videoplayback?expire=1632689184&ei=wIdQYeDzFLCGssUPr6OzoAc&ip=137.147.137.77&id=o-ADuOP6mq-6W7_a9e4vMsdb3psW7QPFoFkQVP4lSE_97W&itag=243&source=youtube&requiressl=yes&mh=Pl&mm=31%2C29&mn=sn-uxanug5-hxael%2Csn-hxa7zn7s&ms=au%2Crdu&mv=m&mvi=3&pl=18&initcwndbps=1747500&vprv=1&mime=video%2Fwebm&gir=yes&clen=15976634&dur=789.288&lmt=1533949525856859&mt=1632667252&fvip=3&keepalive=yes&fexp=24001373%2C24007246&c=ANDROID&sparams=expire%2Cei%2Cip%2Cid%2Citag%2Csource%2Crequiressl%2Cvprv%2Cmime%2Cgir%2Cclen%2Cdur%2Clmt&sig=AOq0QJ8wRQIgJsXCMDzXYQE0QkQsKc-TnxjKPmdjNi5LpEBjDP3fULICIQCi6xgDCokiYOKtuZJaGXxtNDuGJaXGnNOwbVeuu6cn0A%3D%3D&lsparams=mh%2Cmm%2Cmn%2Cms%2Cmv%2Cmvi%2Cpl%2Cinitcwndbps&lsig=AG3C_xAwRAIgOosAFNtgc_RoT7D75iertCxahIVoulZtfVjtGykjsa0CICiBiSBFbkRxZpHej-re-H5-R2Xw9Jf1T6n0ok4Qxfno",
      "width": 640,
      "language": "",
      "language_preference": -1,
      "ext": "webm",
      "vcodec": "vp9",
      "acodec": "none",
      "vbr": 161.934,
      "downloader_options": {
        "http_chunk_size": 10485760
      },
      "container": "webm_dash",
      "protocol": "https",
      "video_ext": "webm",
      "audio_ext": "none",
      "format": "243 - 640x360 (360p)",
      "http_headers": {
        "User-Agent": "Mozilla/5.0 (Windows NT 10.0; Win64; x64) AppleWebKit/537.36 (KHTML, like Gecko) Chrome/69.0.3497.48 Safari/537.36",
        "Accept-Charset": "ISO-8859-1,utf-8;q=0.7,*;q=0.7",
        "Accept": "text/html,application/xhtml+xml,application/xml;q=0.9,*/*;q=0.8",
        "Accept-Encoding": "gzip, deflate",
        "Accept-Language": "en-us,en;q=0.5"
      }
    },
    {
      "filesize": 20672859,
      "format_id": "135",
      "format_note": "480p",
      "fps": 30,
      "height": 480,
      "quality": 7,
      "tbr": 209.534,
      "url": "https://r3---sn-uxanug5-hxael.googlevideo.com/videoplayback?expire=1632689184&ei=wIdQYeDzFLCGssUPr6OzoAc&ip=137.147.137.77&id=o-ADuOP6mq-6W7_a9e4vMsdb3psW7QPFoFkQVP4lSE_97W&itag=135&source=youtube&requiressl=yes&mh=Pl&mm=31%2C29&mn=sn-uxanug5-hxael%2Csn-hxa7zn7s&ms=au%2Crdu&mv=m&mvi=3&pl=18&initcwndbps=1747500&vprv=1&mime=video%2Fmp4&gir=yes&clen=20672859&dur=789.288&lmt=1533948717222911&mt=1632667252&fvip=3&keepalive=yes&fexp=24001373%2C24007246&c=ANDROID&sparams=expire%2Cei%2Cip%2Cid%2Citag%2Csource%2Crequiressl%2Cvprv%2Cmime%2Cgir%2Cclen%2Cdur%2Clmt&sig=AOq0QJ8wRQIhANuyuQyVNR6cYGn4FnKjV9ToZExwH6AN1CYcWg2P85FyAiBD6pgP8jucoPEa0Z9tnXEibwEJR4PtDgROPEcb8tJDdw%3D%3D&lsparams=mh%2Cmm%2Cmn%2Cms%2Cmv%2Cmvi%2Cpl%2Cinitcwndbps&lsig=AG3C_xAwRAIgOosAFNtgc_RoT7D75iertCxahIVoulZtfVjtGykjsa0CICiBiSBFbkRxZpHej-re-H5-R2Xw9Jf1T6n0ok4Qxfno",
      "width": 854,
      "language": "",
      "language_preference": -1,
      "ext": "mp4",
      "vcodec": "avc1.4d401f",
      "acodec": "none",
      "vbr": 209.534,
      "downloader_options": {
        "http_chunk_size": 10485760
      },
      "container": "mp4_dash",
      "protocol": "https",
      "video_ext": "mp4",
      "audio_ext": "none",
      "format": "135 - 854x480 (480p)",
      "http_headers": {
        "User-Agent": "Mozilla/5.0 (Windows NT 10.0; Win64; x64) AppleWebKit/537.36 (KHTML, like Gecko) Chrome/69.0.3497.48 Safari/537.36",
        "Accept-Charset": "ISO-8859-1,utf-8;q=0.7,*;q=0.7",
        "Accept": "text/html,application/xhtml+xml,application/xml;q=0.9,*/*;q=0.8",
        "Accept-Encoding": "gzip, deflate",
        "Accept-Language": "en-us,en;q=0.5"
      }
    },
    {
      "filesize": 25695635,
      "format_id": "244",
      "format_note": "480p",
      "fps": 30,
      "height": 480,
      "quality": 7,
      "tbr": 260.443,
      "url": "https://r3---sn-uxanug5-hxael.googlevideo.com/videoplayback?expire=1632689184&ei=wIdQYeDzFLCGssUPr6OzoAc&ip=137.147.137.77&id=o-ADuOP6mq-6W7_a9e4vMsdb3psW7QPFoFkQVP4lSE_97W&itag=244&source=youtube&requiressl=yes&mh=Pl&mm=31%2C29&mn=sn-uxanug5-hxael%2Csn-hxa7zn7s&ms=au%2Crdu&mv=m&mvi=3&pl=18&initcwndbps=1747500&vprv=1&mime=video%2Fwebm&gir=yes&clen=25695635&dur=789.288&lmt=1533949525884165&mt=1632667252&fvip=3&keepalive=yes&fexp=24001373%2C24007246&c=ANDROID&sparams=expire%2Cei%2Cip%2Cid%2Citag%2Csource%2Crequiressl%2Cvprv%2Cmime%2Cgir%2Cclen%2Cdur%2Clmt&sig=AOq0QJ8wRgIhAIamhilE0qMHnQ3cuTW6A7ymWhoO65fXC5zS2_uG6wjRAiEA03dLjeeDT84mDZWFuLZRer6t25v9SklCKQG7LsLWE20%3D&lsparams=mh%2Cmm%2Cmn%2Cms%2Cmv%2Cmvi%2Cpl%2Cinitcwndbps&lsig=AG3C_xAwRAIgOosAFNtgc_RoT7D75iertCxahIVoulZtfVjtGykjsa0CICiBiSBFbkRxZpHej-re-H5-R2Xw9Jf1T6n0ok4Qxfno",
      "width": 854,
      "language": "",
      "language_preference": -1,
      "ext": "webm",
      "vcodec": "vp9",
      "acodec": "none",
      "vbr": 260.443,
      "downloader_options": {
        "http_chunk_size": 10485760
      },
      "container": "webm_dash",
      "protocol": "https",
      "video_ext": "webm",
      "audio_ext": "none",
      "format": "244 - 854x480 (480p)",
      "http_headers": {
        "User-Agent": "Mozilla/5.0 (Windows NT 10.0; Win64; x64) AppleWebKit/537.36 (KHTML, like Gecko) Chrome/69.0.3497.48 Safari/537.36",
        "Accept-Charset": "ISO-8859-1,utf-8;q=0.7,*;q=0.7",
        "Accept": "text/html,application/xhtml+xml,application/xml;q=0.9,*/*;q=0.8",
        "Accept-Encoding": "gzip, deflate",
        "Accept-Language": "en-us,en;q=0.5"
      }
    },
    {
      "filesize": 33178815,
      "format_id": "136",
      "format_note": "720p",
      "fps": 30,
      "height": 720,
      "quality": 8,
      "tbr": 336.291,
      "url": "https://r3---sn-uxanug5-hxael.googlevideo.com/videoplayback?expire=1632689184&ei=wIdQYeDzFLCGssUPr6OzoAc&ip=137.147.137.77&id=o-ADuOP6mq-6W7_a9e4vMsdb3psW7QPFoFkQVP4lSE_97W&itag=136&source=youtube&requiressl=yes&mh=Pl&mm=31%2C29&mn=sn-uxanug5-hxael%2Csn-hxa7zn7s&ms=au%2Crdu&mv=m&mvi=3&pl=18&initcwndbps=1747500&vprv=1&mime=video%2Fmp4&gir=yes&clen=33178815&dur=789.288&lmt=1533948717524430&mt=1632667252&fvip=3&keepalive=yes&fexp=24001373%2C24007246&c=ANDROID&sparams=expire%2Cei%2Cip%2Cid%2Citag%2Csource%2Crequiressl%2Cvprv%2Cmime%2Cgir%2Cclen%2Cdur%2Clmt&sig=AOq0QJ8wRgIhAMAshMWKsEyVzzLsbubbkMOMsq09af0pmQ5-fSsmd4zDAiEAwNdU_8zYhhaI7QwA0JH5U5FbvHPhGiZFC1dx0bwds_E%3D&lsparams=mh%2Cmm%2Cmn%2Cms%2Cmv%2Cmvi%2Cpl%2Cinitcwndbps&lsig=AG3C_xAwRAIgOosAFNtgc_RoT7D75iertCxahIVoulZtfVjtGykjsa0CICiBiSBFbkRxZpHej-re-H5-R2Xw9Jf1T6n0ok4Qxfno",
      "width": 1280,
      "language": "",
      "language_preference": -1,
      "ext": "mp4",
      "vcodec": "avc1.4d401f",
      "acodec": "none",
      "vbr": 336.291,
      "downloader_options": {
        "http_chunk_size": 10485760
      },
      "container": "mp4_dash",
      "protocol": "https",
      "video_ext": "mp4",
      "audio_ext": "none",
      "format": "136 - 1280x720 (720p)",
      "http_headers": {
        "User-Agent": "Mozilla/5.0 (Windows NT 10.0; Win64; x64) AppleWebKit/537.36 (KHTML, like Gecko) Chrome/69.0.3497.48 Safari/537.36",
        "Accept-Charset": "ISO-8859-1,utf-8;q=0.7,*;q=0.7",
        "Accept": "text/html,application/xhtml+xml,application/xml;q=0.9,*/*;q=0.8",
        "Accept-Encoding": "gzip, deflate",
        "Accept-Language": "en-us,en;q=0.5"
      }
    },
    {
      "asr": 44100,
      "format_id": "22",
      "format_note": "720p",
      "fps": 30,
      "height": 720,
      "quality": 8,
      "tbr": 462.728,
      "url": "https://r3---sn-uxanug5-hxael.googlevideo.com/videoplayback?expire=1632689184&ei=wIdQYeDzFLCGssUPr6OzoAc&ip=137.147.137.77&id=o-ADuOP6mq-6W7_a9e4vMsdb3psW7QPFoFkQVP4lSE_97W&itag=22&source=youtube&requiressl=yes&mh=Pl&mm=31%2C29&mn=sn-uxanug5-hxael%2Csn-hxa7zn7s&ms=au%2Crdu&mv=m&mvi=3&pl=18&initcwndbps=1747500&vprv=1&mime=video%2Fmp4&cnr=14&ratebypass=yes&dur=789.339&lmt=1533950225309975&mt=1632667252&fvip=3&fexp=24001373%2C24007246&c=ANDROID&sparams=expire%2Cei%2Cip%2Cid%2Citag%2Csource%2Crequiressl%2Cvprv%2Cmime%2Ccnr%2Cratebypass%2Cdur%2Clmt&sig=AOq0QJ8wRgIhAI1xyAGSEv3pUWnqw8HNVRQaqCOgu8CMB_6joQzaW8BMAiEAvLdzI_RblX_CjKK-U_4QToGimGMviwe4Ua1xF0X3mWM%3D&lsparams=mh%2Cmm%2Cmn%2Cms%2Cmv%2Cmvi%2Cpl%2Cinitcwndbps&lsig=AG3C_xAwRAIgOosAFNtgc_RoT7D75iertCxahIVoulZtfVjtGykjsa0CICiBiSBFbkRxZpHej-re-H5-R2Xw9Jf1T6n0ok4Qxfno",
      "width": 1280,
      "language": "",
      "language_preference": -1,
      "ext": "mp4",
      "vcodec": "avc1.64001F",
      "acodec": "mp4a.40.2",
      "protocol": "https",
      "video_ext": "mp4",
      "audio_ext": "none",
      "vbr": 462.728,
      "abr": 0.0,
      "format": "22 - 1280x720 (720p)",
      "http_headers": {
        "User-Agent": "Mozilla/5.0 (Windows NT 10.0; Win64; x64) AppleWebKit/537.36 (KHTML, like Gecko) Chrome/69.0.3497.48 Safari/537.36",
        "Accept-Charset": "ISO-8859-1,utf-8;q=0.7,*;q=0.7",
        "Accept": "text/html,application/xhtml+xml,application/xml;q=0.9,*/*;q=0.8",
        "Accept-Encoding": "gzip, deflate",
        "Accept-Language": "en-us,en;q=0.5"
      }
    },
    {
      "filesize": 43984066,
      "format_id": "247",
      "format_note": "720p",
      "fps": 30,
      "height": 720,
      "quality": 8,
      "tbr": 445.81,
      "url": "https://r3---sn-uxanug5-hxael.googlevideo.com/videoplayback?expire=1632689184&ei=wIdQYeDzFLCGssUPr6OzoAc&ip=137.147.137.77&id=o-ADuOP6mq-6W7_a9e4vMsdb3psW7QPFoFkQVP4lSE_97W&itag=247&source=youtube&requiressl=yes&mh=Pl&mm=31%2C29&mn=sn-uxanug5-hxael%2Csn-hxa7zn7s&ms=au%2Crdu&mv=m&mvi=3&pl=18&initcwndbps=1747500&vprv=1&mime=video%2Fwebm&gir=yes&clen=43984066&dur=789.288&lmt=1533949525883386&mt=1632667252&fvip=3&keepalive=yes&fexp=24001373%2C24007246&c=ANDROID&sparams=expire%2Cei%2Cip%2Cid%2Citag%2Csource%2Crequiressl%2Cvprv%2Cmime%2Cgir%2Cclen%2Cdur%2Clmt&sig=AOq0QJ8wRQIhAPvxRDm85Qdz8qON7x0S4SXjd5-nJFHU9LJrbMu3M7rTAiAJQvwmO8e8WL_J4sBObAXciQAv8qv9JcB-dljryteI0Q%3D%3D&lsparams=mh%2Cmm%2Cmn%2Cms%2Cmv%2Cmvi%2Cpl%2Cinitcwndbps&lsig=AG3C_xAwRAIgOosAFNtgc_RoT7D75iertCxahIVoulZtfVjtGykjsa0CICiBiSBFbkRxZpHej-re-H5-R2Xw9Jf1T6n0ok4Qxfno",
      "width": 1280,
      "language": "",
      "language_preference": -1,
      "ext": "webm",
      "vcodec": "vp9",
      "acodec": "none",
      "vbr": 445.81,
      "downloader_options": {
        "http_chunk_size": 10485760
      },
      "container": "webm_dash",
      "protocol": "https",
      "video_ext": "webm",
      "audio_ext": "none",
      "format": "247 - 1280x720 (720p)",
      "http_headers": {
        "User-Agent": "Mozilla/5.0 (Windows NT 10.0; Win64; x64) AppleWebKit/537.36 (KHTML, like Gecko) Chrome/69.0.3497.48 Safari/537.36",
        "Accept-Charset": "ISO-8859-1,utf-8;q=0.7,*;q=0.7",
        "Accept": "text/html,application/xhtml+xml,application/xml;q=0.9,*/*;q=0.8",
        "Accept-Encoding": "gzip, deflate",
        "Accept-Language": "en-us,en;q=0.5"
      }
    },
    {
      "filesize": 59613756,
      "format_id": "137",
      "format_note": "1080p",
      "fps": 30,
      "height": 1080,
      "quality": 9,
      "tbr": 604.228,
      "url": "https://r3---sn-uxanug5-hxael.googlevideo.com/videoplayback?expire=1632689184&ei=wIdQYeDzFLCGssUPr6OzoAc&ip=137.147.137.77&id=o-ADuOP6mq-6W7_a9e4vMsdb3psW7QPFoFkQVP4lSE_97W&itag=137&source=youtube&requiressl=yes&mh=Pl&mm=31%2C29&mn=sn-uxanug5-hxael%2Csn-hxa7zn7s&ms=au%2Crdu&mv=m&mvi=3&pl=18&initcwndbps=1747500&vprv=1&mime=video%2Fmp4&gir=yes&clen=59613756&dur=789.288&lmt=1533948795161804&mt=1632667252&fvip=3&keepalive=yes&fexp=24001373%2C24007246&c=ANDROID&sparams=expire%2Cei%2Cip%2Cid%2Citag%2Csource%2Crequiressl%2Cvprv%2Cmime%2Cgir%2Cclen%2Cdur%2Clmt&sig=AOq0QJ8wRAIgDXSH3DFP_FGQK4TWcn5A58zxFTgZvPRud3IaYVAFFksCIFD1r7RffORDeGBIz2VKaoIpOYzrPU5XL9ftrqzNkR5W&lsparams=mh%2Cmm%2Cmn%2Cms%2Cmv%2Cmvi%2Cpl%2Cinitcwndbps&lsig=AG3C_xAwRAIgOosAFNtgc_RoT7D75iertCxahIVoulZtfVjtGykjsa0CICiBiSBFbkRxZpHej-re-H5-R2Xw9Jf1T6n0ok4Qxfno",
      "width": 1920,
      "language": "",
      "language_preference": -1,
      "ext": "mp4",
      "vcodec": "avc1.640028",
      "acodec": "none",
      "vbr": 604.228,
      "downloader_options": {
        "http_chunk_size": 10485760
      },
      "container": "mp4_dash",
      "protocol": "https",
      "video_ext": "mp4",
      "audio_ext": "none",
      "format": "137 - 1920x1080 (1080p)",
      "http_headers": {
        "User-Agent": "Mozilla/5.0 (Windows NT 10.0; Win64; x64) AppleWebKit/537.36 (KHTML, like Gecko) Chrome/69.0.3497.48 Safari/537.36",
        "Accept-Charset": "ISO-8859-1,utf-8;q=0.7,*;q=0.7",
        "Accept": "text/html,application/xhtml+xml,application/xml;q=0.9,*/*;q=0.8",
        "Accept-Encoding": "gzip, deflate",
        "Accept-Language": "en-us,en;q=0.5"
      }
    },
    {
      "filesize": 76292635,
      "format_id": "248",
      "format_note": "1080p",
      "fps": 30,
      "height": 1080,
      "quality": 9,
      "tbr": 773.28,
      "url": "https://r3---sn-uxanug5-hxael.googlevideo.com/videoplayback?expire=1632689184&ei=wIdQYeDzFLCGssUPr6OzoAc&ip=137.147.137.77&id=o-ADuOP6mq-6W7_a9e4vMsdb3psW7QPFoFkQVP4lSE_97W&itag=248&source=youtube&requiressl=yes&mh=Pl&mm=31%2C29&mn=sn-uxanug5-hxael%2Csn-hxa7zn7s&ms=au%2Crdu&mv=m&mvi=3&pl=18&initcwndbps=1747500&vprv=1&mime=video%2Fwebm&gir=yes&clen=76292635&dur=789.288&lmt=1533950271514331&mt=1632667252&fvip=3&keepalive=yes&fexp=24001373%2C24007246&c=ANDROID&sparams=expire%2Cei%2Cip%2Cid%2Citag%2Csource%2Crequiressl%2Cvprv%2Cmime%2Cgir%2Cclen%2Cdur%2Clmt&sig=AOq0QJ8wRAIgDyspuKMTwaH1V5hJ3eNAbwZBb7Ra1rzzeHR6dFniIe8CIEpvWiYyis3WTdAc7eC0UKG15dGAYIgBU_xQf2vzP0yY&lsparams=mh%2Cmm%2Cmn%2Cms%2Cmv%2Cmvi%2Cpl%2Cinitcwndbps&lsig=AG3C_xAwRAIgOosAFNtgc_RoT7D75iertCxahIVoulZtfVjtGykjsa0CICiBiSBFbkRxZpHej-re-H5-R2Xw9Jf1T6n0ok4Qxfno",
      "width": 1920,
      "language": "",
      "language_preference": -1,
      "ext": "webm",
      "vcodec": "vp9",
      "acodec": "none",
      "vbr": 773.28,
      "downloader_options": {
        "http_chunk_size": 10485760
      },
      "container": "webm_dash",
      "protocol": "https",
      "video_ext": "webm",
      "audio_ext": "none",
      "format": "248 - 1920x1080 (1080p)",
      "http_headers": {
        "User-Agent": "Mozilla/5.0 (Windows NT 10.0; Win64; x64) AppleWebKit/537.36 (KHTML, like Gecko) Chrome/69.0.3497.48 Safari/537.36",
        "Accept-Charset": "ISO-8859-1,utf-8;q=0.7,*;q=0.7",
        "Accept": "text/html,application/xhtml+xml,application/xml;q=0.9,*/*;q=0.8",
        "Accept-Encoding": "gzip, deflate",
        "Accept-Language": "en-us,en;q=0.5"
      }
    }
  ],
  "thumbnails": [
    {
      "url": "https://i.ytimg.com/vi/azvFmffyuS4/3.jpg",
      "preference": -37,
      "id": "0"
    },
    {
      "url": "https://i.ytimg.com/vi_webp/azvFmffyuS4/3.webp",
      "preference": -36,
      "id": "1"
    },
    {
      "url": "https://i.ytimg.com/vi/azvFmffyuS4/2.jpg",
      "preference": -35,
      "id": "2"
    },
    {
      "url": "https://i.ytimg.com/vi_webp/azvFmffyuS4/2.webp",
      "preference": -34,
      "id": "3"
    },
    {
      "url": "https://i.ytimg.com/vi/azvFmffyuS4/1.jpg",
      "preference": -33,
      "id": "4"
    },
    {
      "url": "https://i.ytimg.com/vi_webp/azvFmffyuS4/1.webp",
      "preference": -32,
      "id": "5"
    },
    {
      "url": "https://i.ytimg.com/vi/azvFmffyuS4/default.jpg",
      "preference": -31,
      "id": "6"
    },
    {
      "url": "https://i.ytimg.com/vi_webp/azvFmffyuS4/default.webp",
      "height": 90,
      "width": 120,
      "preference": -30,
      "id": "7",
      "resolution": "120x90"
    },
    {
      "url": "https://i.ytimg.com/vi/azvFmffyuS4/mq3.jpg",
      "preference": -29,
      "id": "8"
    },
    {
      "url": "https://i.ytimg.com/vi_webp/azvFmffyuS4/mq3.webp",
      "preference": -28,
      "id": "9"
    },
    {
      "url": "https://i.ytimg.com/vi/azvFmffyuS4/mq2.jpg",
      "preference": -27,
      "id": "10"
    },
    {
      "url": "https://i.ytimg.com/vi_webp/azvFmffyuS4/mq2.webp",
      "preference": -26,
      "id": "11"
    },
    {
      "url": "https://i.ytimg.com/vi/azvFmffyuS4/mq1.jpg",
      "preference": -25,
      "id": "12"
    },
    {
      "url": "https://i.ytimg.com/vi_webp/azvFmffyuS4/mq1.webp",
      "preference": -24,
      "id": "13"
    },
    {
      "url": "https://i.ytimg.com/vi/azvFmffyuS4/mqdefault.jpg",
      "preference": -23,
      "id": "14"
    },
    {
      "url": "https://i.ytimg.com/vi_webp/azvFmffyuS4/mqdefault.webp",
      "height": 180,
      "width": 320,
      "preference": -22,
      "id": "15",
      "resolution": "320x180"
    },
    {
      "url": "https://i.ytimg.com/vi/azvFmffyuS4/0.jpg",
      "preference": -21,
      "id": "16"
    },
    {
      "url": "https://i.ytimg.com/vi_webp/azvFmffyuS4/0.webp",
      "preference": -20,
      "id": "17"
    },
    {
      "url": "https://i.ytimg.com/vi/azvFmffyuS4/hq3.jpg",
      "preference": -19,
      "id": "18"
    },
    {
      "url": "https://i.ytimg.com/vi_webp/azvFmffyuS4/hq3.webp",
      "preference": -18,
      "id": "19"
    },
    {
      "url": "https://i.ytimg.com/vi/azvFmffyuS4/hq2.jpg",
      "preference": -17,
      "id": "20"
    },
    {
      "url": "https://i.ytimg.com/vi_webp/azvFmffyuS4/hq2.webp",
      "preference": -16,
      "id": "21"
    },
    {
      "url": "https://i.ytimg.com/vi/azvFmffyuS4/hq1.jpg",
      "preference": -15,
      "id": "22"
    },
    {
      "url": "https://i.ytimg.com/vi_webp/azvFmffyuS4/hq1.webp",
      "preference": -14,
      "id": "23"
    },
    {
      "url": "https://i.ytimg.com/vi/azvFmffyuS4/hqdefault.jpg?sqp=-oaymwEbCKgBEF5IVfKriqkDDggBFQAAiEIYAXABwAEG&rs=AOn4CLDcyjrABDqsyxzRLujiFP3EMms_yw",
      "height": 94,
      "width": 168,
      "preference": -13,
      "id": "24",
      "resolution": "168x94"
    },
    {
      "url": "https://i.ytimg.com/vi/azvFmffyuS4/hqdefault.jpg?sqp=-oaymwEbCMQBEG5IVfKriqkDDggBFQAAiEIYAXABwAEG&rs=AOn4CLCNNzYLiPLyqmcyhc9qiw-9yssFsg",
      "height": 110,
      "width": 196,
      "preference": -13,
      "id": "25",
      "resolution": "196x110"
    },
    {
      "url": "https://i.ytimg.com/vi/azvFmffyuS4/hqdefault.jpg?sqp=-oaymwEcCPYBEIoBSFXyq4qpAw4IARUAAIhCGAFwAcABBg==&rs=AOn4CLCoZ-Sksgfzy3Et1JZWG9JCY7lJnA",
      "height": 138,
      "width": 246,
      "preference": -13,
      "id": "26",
      "resolution": "246x138"
    },
    {
      "url": "https://i.ytimg.com/vi/azvFmffyuS4/hqdefault.jpg?sqp=-oaymwEcCNACELwBSFXyq4qpAw4IARUAAIhCGAFwAcABBg==&rs=AOn4CLAtVzpDkANRMKayxfx_I9USx-ypjw",
      "height": 188,
      "width": 336,
      "preference": -13,
      "id": "27",
      "resolution": "336x188"
    },
    {
      "url": "https://i.ytimg.com/vi/azvFmffyuS4/hqdefault.jpg",
      "height": 360,
      "width": 480,
      "preference": -13,
      "id": "28",
      "resolution": "480x360"
    },
    {
      "url": "https://i.ytimg.com/vi_webp/azvFmffyuS4/hqdefault.webp",
      "height": 360,
      "width": 480,
      "preference": -12,
      "id": "29",
      "resolution": "480x360"
    },
    {
      "url": "https://i.ytimg.com/vi/azvFmffyuS4/sd3.jpg",
      "preference": -11,
      "id": "30"
    },
    {
      "url": "https://i.ytimg.com/vi_webp/azvFmffyuS4/sd3.webp",
      "preference": -10,
      "id": "31"
    },
    {
      "url": "https://i.ytimg.com/vi/azvFmffyuS4/sd2.jpg",
      "preference": -9,
      "id": "32"
    },
    {
      "url": "https://i.ytimg.com/vi_webp/azvFmffyuS4/sd2.webp",
      "preference": -8,
      "id": "33"
    },
    {
      "url": "https://i.ytimg.com/vi/azvFmffyuS4/sd1.jpg",
      "preference": -7,
      "id": "34"
    },
    {
      "url": "https://i.ytimg.com/vi_webp/azvFmffyuS4/sd1.webp",
      "preference": -6,
      "id": "35"
    },
    {
      "url": "https://i.ytimg.com/vi/azvFmffyuS4/sddefault.jpg",
      "preference": -5,
      "id": "36"
    },
    {
      "url": "https://i.ytimg.com/vi_webp/azvFmffyuS4/sddefault.webp",
      "height": 480,
      "width": 640,
      "preference": -4,
      "id": "37",
      "resolution": "640x480"
    }
  ],
  "description": "Mindy's birthday is tomorrow and she has talked with her dad for months about how she wants it to be perfect... but will he deliver?",
  "upload_date": "20180810",
  "uploader": "Tamers12345",
  "uploader_id": "Tamers12345",
  "uploader_url": "http://www.youtube.com/user/Tamers12345",
  "channel_id": "UCQLVTT8LkgSOyZ2mD8BU3dA",
  "channel_url": "https://www.youtube.com/channel/UCQLVTT8LkgSOyZ2mD8BU3dA",
  "duration": 789,
  "view_count": 15510,
  "average_rating": 4.8548388,
  "age_limit": 0,
  "webpage_url": "https://www.youtube.com/watch?v=azvFmffyuS4",
  "categories": [
    "Entertainment"
  ],
  "tags": [
    "sonic",
    "manic",
    "sonia",
    "knuckles",
    "underground",
    "hedgehog",
    "echidna",
    "modern",
    "classic",
    "satam",
    "cool",
    "win",
    "lol",
    "owned",
    "fail",
    "react",
    "reaction",
    "opening",
    "ending",
    "manga",
    "animation",
    "anime",
    "naruto",
    "star",
    "wars",
    "obi-wan",
    "kenobi",
    "rey",
    "kylo ren",
    "kylo",
    "anakin",
    "yoda",
    "sidious",
    "snoke",
    "playstation",
    "super",
    "smash",
    "bros",
    "ultimate",
    "switch",
    "wii",
    "wii u",
    "microsoft",
    "x box",
    "xbox",
    "darth",
    "vader",
    "drake",
    "bell",
    "josh",
    "peck",
    "nick",
    "nickelodeon",
    "cartoon",
    "network",
    "disney",
    "channel",
    "animated",
    "funny",
    "cute",
    "sexy",
    "movie",
    "full",
    "lyrics",
    "english",
    "song",
    "happy",
    "sad",
    "dub",
    "sub"
  ],
  "playable_in_embed": true,
  "is_live": false,
  "was_live": false,
  "live_status": "not_live",
  "like_count": 478,
  "dislike_count": 18,
  "channel": "Tamers12345",
  "availability": "public",
  "webpage_url_basename": "watch",
  "extractor": "youtube",
  "extractor_key": "Youtube",
  "n_entries": 632,
  "playlist_index": 201,
  "playlist": "Tamers12345 - Videos",
  "playlist_id": "UCQLVTT8LkgSOyZ2mD8BU3dA",
  "playlist_title": "Tamers12345 - Videos",
  "playlist_uploader": "Tamers12345",
  "playlist_uploader_id": "UCQLVTT8LkgSOyZ2mD8BU3dA",
  "thumbnail": "https://i.ytimg.com/vi_webp/azvFmffyuS4/sddefault.webp",
  "display_id": "azvFmffyuS4",
  "format": "248 - 1920x1080 (1080p)+251 - audio only (medium)",
  "format_id": "248+251",
  "ext": "mkv",
  "width": 1920,
  "height": 1080,
  "resolution": "1920x1080",
  "fps": 30,
  "vcodec": "vp9",
  "vbr": 773.28,
  "acodec": "opus",
  "abr": 117.387,
  "fulltitle": "Sonic Underground - Mindy's Sweet Sixteen!",
  "comments": [
    {
      "id": "UgwMxdYceNdbGLltPdJ4AaABAg",
      "text": "1:45 That did not age quite so well.",
      "timestamp": 1627344000,
      "time_text": "2 months ago",
      "like_count": 4,
      "is_favorited": false,
      "author": "Zachary The Mad",
      "author_id": "UCaolFaDNE8p5mpI7uLR7kmw",
      "author_thumbnail": "https://yt3.ggpht.com/ytc/AKedOLT0a-CfUL8LPjhxcOm-t5WgvpxULuAIj34rLL2PmQ=s176-c-k-c0x00ffffff-no-rj",
      "author_is_uploader": false,
      "parent": "root"
    },
    {
      "id": "Ugy5ixyCa8nrXbEMoUh4AaABAg",
      "text": "Came back to rewatch after the last episode, gotta say the light beam at 11:46 was great",
      "timestamp": 1627344000,
      "time_text": "2 months ago",
      "like_count": 3,
      "is_favorited": false,
      "author": "Hou",
      "author_id": "UCipbFExJtfx31Shjh97fCsQ",
      "author_thumbnail": "https://yt3.ggpht.com/ytc/AKedOLQ6CfDWxoa5zCNT2T-5nTM32tVTJWinvotSP8siKg=s176-c-k-c0x00ffffff-no-rj",
      "author_is_uploader": false,
      "parent": "root"
    },
    {
      "id": "UgzPzmyoqfP5AmWRkCp4AaABAg",
      "text": "This is so deep and emotional you are truly brilliant tamers",
      "timestamp": 1616803200,
      "time_text": "6 months ago",
      "like_count": 2,
      "is_favorited": false,
      "author": "the ultimate Tamers one two three four five fan",
      "author_id": "UCv9kzw7j04IKQREAlk4614g",
      "author_thumbnail": "https://yt3.ggpht.com/ytc/AKedOLRG--Wmlyoj903bvXrVnP28AHyKYDSTgrGuLELw=s176-c-k-c0x00ffffff-no-rj",
      "author_is_uploader": false,
      "parent": "root"
    },
    {
      "id": "Ugz_Y2y4OHcD7PW916V4AaABAg",
      "text": "i...\ni have no words. not in the positive way, all of this was awful. horrible job everyone",
      "timestamp": 1614384000,
      "time_text": "7 months ago",
      "like_count": 0,
      "is_favorited": false,
      "author": "Reese Leones",
      "author_id": "UCQ94zK8haYWxfYz5y4bMwsg",
      "author_thumbnail": "https://yt3.ggpht.com/ytc/AKedOLQv3G7OiW0bIVThJXcrIsJBXi_rmt5UjV8fUpV3uQ=s176-c-k-c0x00ffffff-no-rj",
      "author_is_uploader": false,
      "parent": "root",
      "replies": [
        {
          "id": "Ugz_Y2y4OHcD7PW916V4AaABAg.9K81sg9SYFb9NmT_VpXOx_",
          "text": "Modern sonic fan?! 😤😤",
          "timestamp": 1622073600,
          "time_text": "4 months ago (edited)",
          "like_count": 1,
          "is_favorited": false,
          "author": "Alisha C. Browne",
          "author_id": "UCgsJqTfeTe8fgxbbSLdhxeg",
          "author_thumbnail": "https://yt3.ggpht.com/o9gR4UsJTVUHGm0zLewj2zQMl368QHI3hUaBMH6IILb3wiSbpFFRBuPyEjbFCXHmynH-sMHObA=s176-c-k-c0x00ffffff-no-rj",
          "author_is_uploader": false,
          "parent": "Ugz_Y2y4OHcD7PW916V4AaABAg"
        },
        {
          "id": "Ugz_Y2y4OHcD7PW916V4AaABAg.9K81sg9SYFb9NmUVBVss5v",
          "text": " @Alisha C. Browne  no, sonic anti",
          "timestamp": 1622073600,
          "time_text": "4 months ago",
          "like_count": 0,
          "is_favorited": false,
          "author": "Reese Leones",
          "author_id": "UCQ94zK8haYWxfYz5y4bMwsg",
          "author_thumbnail": "https://yt3.ggpht.com/ytc/AKedOLQv3G7OiW0bIVThJXcrIsJBXi_rmt5UjV8fUpV3uQ=s176-c-k-c0x00ffffff-no-rj",
          "author_is_uploader": false,
          "parent": "Ugz_Y2y4OHcD7PW916V4AaABAg"
        },
        {
          "id": "Ugz_Y2y4OHcD7PW916V4AaABAg.9K81sg9SYFb9NmV6GzQHwC",
          "text": " @Reese Leones  Wait nvm lol. But don't talk smack about the god of Sonic Understand. 😠",
          "timestamp": 1622073600,
          "time_text": "4 months ago",
          "like_count": 1,
          "is_favorited": false,
          "author": "Alisha C. Browne",
          "author_id": "UCgsJqTfeTe8fgxbbSLdhxeg",
          "author_thumbnail": "https://yt3.ggpht.com/o9gR4UsJTVUHGm0zLewj2zQMl368QHI3hUaBMH6IILb3wiSbpFFRBuPyEjbFCXHmynH-sMHObA=s176-c-k-c0x00ffffff-no-rj",
          "author_is_uploader": false,
          "parent": "Ugz_Y2y4OHcD7PW916V4AaABAg"
        }
      ]
    },
    {
      "id": "UgxxaOIevm1vF4o3EAJ4AaABAg",
      "text": "2:35 11:37 Very Good Animation Gif",
      "timestamp": 1614384000,
      "time_text": "7 months ago (edited)",
      "like_count": 1,
      "is_favorited": false,
      "author": "ZekeyX2004",
      "author_id": "UC5t7OSkcFIt8I0GTWvB3EVw",
      "author_thumbnail": "https://yt3.ggpht.com/ytc/AKedOLT3wBcgaX1VpXMcQ2f2RI3T2t_92RFK-Mv3y0AFpA=s176-c-k-c0x00ffffff-no-rj",
      "author_is_uploader": false,
      "parent": "root"
    },
    {
      "id": "UgzkCogX9I3noF2_mFh4AaABAg",
      "text": "Bartleby is so cute doing his dance",
      "timestamp": 1606435200,
      "time_text": "10 months ago",
      "like_count": 5,
      "is_favorited": false,
      "author": "Suicidal Spectre",
      "author_id": "UCgTVLuMbQLKhAeO7rbmNKDg",
      "author_thumbnail": "https://yt3.ggpht.com/kGDJjGH00WSiUfIA3_1j-2MknuJUeAg1HBZ0RUil_w_EyfFRStShWBICKr1NOefOEdibMGDF9H4=s176-c-k-c0x00ffffff-no-rj",
      "author_is_uploader": false,
      "parent": "root"
    },
    {
      "id": "Ugwxdwb6owRPCwxhlpF4AaABAg",
      "text": "Why is she naked 😮 5:19",
      "timestamp": 1601164800,
      "time_text": "1 year ago",
      "like_count": 3,
      "is_favorited": false,
      "author": "Chastity Otter",
      "author_id": "UCOOUMTFq0EN0v0AchIFp_kQ",
      "author_thumbnail": "https://yt3.ggpht.com/ytc/AKedOLQwpL_XLWtYhxe4U5oS7ZAJRHy-LGU4sT-6LiCisA=s176-c-k-c0x00ffffff-no-rj",
      "author_is_uploader": false,
      "parent": "root"
    },
    {
      "id": "UgwCrqy64Ptwu31lW1x4AaABAg",
      "text": "7:04",
      "timestamp": 1601164800,
      "time_text": "1 year ago (edited)",
      "like_count": 2,
      "is_favorited": false,
      "author": "Ale Titan",
      "author_id": "UC-eH6kZzhIq9uAC4FiLlL8w",
      "author_thumbnail": "https://yt3.ggpht.com/ytc/AKedOLRuEEjHg_SvmNmmt4ZOUnzx6Ntzohr3e_DNk7puTw=s176-c-k-c0x00ffffff-no-rj",
      "author_is_uploader": false,
      "parent": "root"
    },
    {
      "id": "UgyYjstSyg5-lSX8-614AaABAg",
      "text": "Cracka looks as happy as a truck Highlander with big tires",
      "timestamp": 1601164800,
      "time_text": "1 year ago",
      "like_count": 1,
      "is_favorited": false,
      "author": "Jane H",
      "author_id": "UCEiYu2laNSbwsUX-rsTUxFQ",
      "author_thumbnail": "https://yt3.ggpht.com/ytc/AKedOLTQvGBBBxd7i5eBxfBVMTmbYmQcWBohlGocSg=s176-c-k-c0x00ffffff-no-rj",
      "author_is_uploader": false,
      "parent": "root"
    },
    {
      "id": "UgxbvuZJI5doGQzmt2t4AaABAg",
      "text": "Can you add straight couples. I've seen your vids and it almost all gay references. Especially with sonic and that ugly blonde snobby made character. Its just disgusting and an abomination!!!",
      "timestamp": 1569542400,
      "time_text": "2 years ago",
      "like_count": 8,
      "is_favorited": false,
      "author": "Goldenjem Summerlight",
      "author_id": "UCKUkRHb80Ix4O7bkHIhDVpg",
      "author_thumbnail": "https://yt3.ggpht.com/ytc/AKedOLS_3Esx-yjwhnVW8AIP3VONq6-G5rxIXh50_hanlQ=s176-c-k-c0x00ffffff-no-rj",
      "author_is_uploader": false,
      "parent": "root",
      "replies": [
        {
          "id": "UgxbvuZJI5doGQzmt2t4AaABAg.8yBK_R5G_eV8yn-80QcETc",
          "text": "It's a fictional world, just enjoy the show",
          "timestamp": 1569542400,
          "time_text": "2 years ago",
          "like_count": 5,
          "is_favorited": false,
          "author": "♡Misha♡",
          "author_id": "UClCrkgWXNKGqejJM_FxG88Q",
          "author_thumbnail": "https://yt3.ggpht.com/m_AeNPpIRjiWkCGG1y2rT7s-kISJIGR2XpWTFDxWJUOEnVEUsxtTv0udRUkQBxDd-EF2vaSsxw=s176-c-k-c0x00ffffff-no-rj",
          "author_is_uploader": false,
          "parent": "UgxbvuZJI5doGQzmt2t4AaABAg"
        },
        {
          "id": "UgxbvuZJI5doGQzmt2t4AaABAg.8yBK_R5G_eV8yrGszk4oHv",
          "text": " @♡Misha♡  I know its just a cartoon but come on, Mindys father abusing her, bartleby smaking sonic's a$% all the time like a pervert and that crazy so called drunk grandfather of theirs. \n\nThis is unacceptable!!!",
          "timestamp": 1569542400,
          "time_text": "2 years ago",
          "like_count": 5,
          "is_favorited": false,
          "author": "Goldenjem Summerlight",
          "author_id": "UCKUkRHb80Ix4O7bkHIhDVpg",
          "author_thumbnail": "https://yt3.ggpht.com/ytc/AKedOLS_3Esx-yjwhnVW8AIP3VONq6-G5rxIXh50_hanlQ=s176-c-k-c0x00ffffff-no-rj",
          "author_is_uploader": false,
          "parent": "UgxbvuZJI5doGQzmt2t4AaABAg"
        },
        {
          "id": "UgxbvuZJI5doGQzmt2t4AaABAg.8yBK_R5G_eV8yrHpqQHI2g",
          "text": " @Goldenjem Summerlight  I get what your saying since some themes are a bit much, but it's the creators style and we should accept it.",
          "timestamp": 1569542400,
          "time_text": "2 years ago",
          "like_count": 5,
          "is_favorited": false,
          "author": "♡Misha♡",
          "author_id": "UClCrkgWXNKGqejJM_FxG88Q",
          "author_thumbnail": "https://yt3.ggpht.com/m_AeNPpIRjiWkCGG1y2rT7s-kISJIGR2XpWTFDxWJUOEnVEUsxtTv0udRUkQBxDd-EF2vaSsxw=s176-c-k-c0x00ffffff-no-rj",
          "author_is_uploader": false,
          "parent": "UgxbvuZJI5doGQzmt2t4AaABAg"
        },
        {
          "id": "UgxbvuZJI5doGQzmt2t4AaABAg.8yBK_R5G_eV9AOAGNdY9NG",
          "text": "dude is probably gay",
          "timestamp": 1601164800,
          "time_text": "1 year ago",
          "like_count": 0,
          "is_favorited": false,
          "author": "Vinx",
          "author_id": "UC0JQmJE4uS4bScFM5d_keKQ",
          "author_thumbnail": "https://yt3.ggpht.com/ytc/AKedOLRV6m9wgObCRwhazu6CrB5rRzRxKqnhp8jHE-BH=s176-c-k-c0x00ffffff-no-rj",
          "author_is_uploader": false,
          "parent": "UgxbvuZJI5doGQzmt2t4AaABAg"
        },
        {
          "id": "UgxbvuZJI5doGQzmt2t4AaABAg.8yBK_R5G_eV9AOAIPk_brK",
          "text": "thats why people pretend to like it. i notice people give stupid shit a pass as long as it's gay.",
          "timestamp": 1601164800,
          "time_text": "1 year ago",
          "like_count": 0,
          "is_favorited": false,
          "author": "Vinx",
          "author_id": "UC0JQmJE4uS4bScFM5d_keKQ",
          "author_thumbnail": "https://yt3.ggpht.com/ytc/AKedOLRV6m9wgObCRwhazu6CrB5rRzRxKqnhp8jHE-BH=s176-c-k-c0x00ffffff-no-rj",
          "author_is_uploader": false,
          "parent": "UgxbvuZJI5doGQzmt2t4AaABAg"
        },
        {
          "id": "UgxbvuZJI5doGQzmt2t4AaABAg.8yBK_R5G_eV9PXJRaGZbgA",
          "text": " @Vinx  The irony is lost in you",
          "timestamp": 1627344000,
          "time_text": "2 months ago",
          "like_count": 0,
          "is_favorited": false,
          "author": "Hou",
          "author_id": "UCipbFExJtfx31Shjh97fCsQ",
          "author_thumbnail": "https://yt3.ggpht.com/ytc/AKedOLQ6CfDWxoa5zCNT2T-5nTM32tVTJWinvotSP8siKg=s176-c-k-c0x00ffffff-no-rj",
          "author_is_uploader": false,
          "parent": "UgxbvuZJI5doGQzmt2t4AaABAg"
        }
      ]
    },
    {
      "id": "Ugx2_p6NZ7gXLBgpPAB4AaABAg",
      "text": ";-;",
      "timestamp": 1569542400,
      "time_text": "2 years ago",
      "like_count": 0,
      "is_favorited": false,
      "author": "RoVin [GeoDash]",
      "author_id": "UCnaC2S8lmaxRXEuJmH4mouA",
      "author_thumbnail": "https://yt3.ggpht.com/ytc/AKedOLQrdiB4yLZHg9IDxq7Ig0g_UKQJd8ie78FltNGiJw=s176-c-k-c0x00ffffff-no-rj",
      "author_is_uploader": false,
      "parent": "root"
    },
    {
      "id": "UgyltxEAvg1Fc56il_t4AaABAg",
      "text": "Mindys dad rocking out some REM?",
      "timestamp": 1569542400,
      "time_text": "2 years ago",
      "like_count": 0,
      "is_favorited": false,
      "author": "Brando Zero",
      "author_id": "UCdxWJ85DLFxICuSSrmoPMCQ",
      "author_thumbnail": "https://yt3.ggpht.com/ytc/AKedOLQD3E8yL4Ew2wyRpOSprpzLDBzI-dQvCptH2p6J=s176-c-k-c0x00ffffff-no-rj",
      "author_is_uploader": false,
      "parent": "root"
    },
    {
      "id": "UgwfhENkfd6tGQBtZYF4AaABAg",
      "text": "WHYYYY",
      "timestamp": 1569542400,
      "time_text": "2 years ago",
      "like_count": 1,
      "is_favorited": false,
      "author": "Jackie",
      "author_id": "UCRSDFf7cVeCxL2Wjui0I_aw",
      "author_thumbnail": "https://yt3.ggpht.com/ytc/AKedOLSnbZIcVK8VPsRkzuG5tySYYPy7ZMQWdB1W361AXjA=s176-c-k-c0x00ffffff-no-rj",
      "author_is_uploader": false,
      "parent": "root"
    },
    {
      "id": "UgyJI06eEKUijz5b2_N4AaABAg",
      "text": "MINDY IS MANIC'S GIRLFRIEND WHAT? And manic JUST WATCHED HER GO FUCK A CLOWN XKJDJSBSSBSHD",
      "timestamp": 1569542400,
      "time_text": "2 years ago",
      "like_count": 2,
      "is_favorited": false,
      "author": "Subject28 X",
      "author_id": "UC7FIBILoKPA0cucAYwlizbw",
      "author_thumbnail": "https://yt3.ggpht.com/ytc/AKedOLQFj6J2adxR0PtvhwRatFyt8yjgmph5u6Jr16sKqA=s176-c-k-c0x00ffffff-no-rj",
      "author_is_uploader": false,
      "parent": "root"
    },
    {
      "id": "Ugz1G_EDSiWTDxzHSIB4AaABAg",
      "text": "HER MOM IS DEAD OK THAT'S SO SAD",
      "timestamp": 1569542400,
      "time_text": "2 years ago",
      "like_count": 8,
      "is_favorited": false,
      "author": "Subject28 X",
      "author_id": "UC7FIBILoKPA0cucAYwlizbw",
      "author_thumbnail": "https://yt3.ggpht.com/ytc/AKedOLQFj6J2adxR0PtvhwRatFyt8yjgmph5u6Jr16sKqA=s176-c-k-c0x00ffffff-no-rj",
      "author_is_uploader": false,
      "parent": "root"
    },
    {
      "id": "UgxTvWZTFJaJNb8cmqp4AaABAg",
      "text": "Epic",
      "timestamp": 1569542400,
      "time_text": "2 years ago",
      "like_count": 1,
      "is_favorited": false,
      "author": "EpicLOLGuy",
      "author_id": "UCZzwDGKFnb_e92UVreL55vg",
      "author_thumbnail": "https://yt3.ggpht.com/ytc/AKedOLQuIOVI0UMnZkV_J7H935EKakcLnONnfOTHMVoisQ=s176-c-k-c0x00ffffff-no-rj",
      "author_is_uploader": false,
      "parent": "root"
    },
    {
      "id": "UgwDUOu89IbfeSgkjrt4AaABAg",
      "text": "Where can I get those AT&T voices?",
      "timestamp": 1569542400,
      "time_text": "2 years ago",
      "like_count": 2,
      "is_favorited": false,
      "author": "Darren Pipster Studios",
      "author_id": "UCIuk7BhcUqbrhxduQ7VUbnw",
      "author_thumbnail": "https://yt3.ggpht.com/rkJUN5sJW0QOd3pgEZABwhmXJuz5AbIu_mGqWjNwJOnMyIKxRP0ub9r1B3g3hRIoMhD55hSC=s176-c-k-c0x00ffffff-no-rj",
      "author_is_uploader": false,
      "parent": "root"
    },
    {
      "id": "UgyLdACRdsP3F07IlNh4AaABAg",
      "text": "Ok I'm going to go kill myself because of this fucked up shit",
      "timestamp": 1569542400,
      "time_text": "2 years ago",
      "like_count": 1,
      "is_favorited": false,
      "author": "Tanya Garduno",
      "author_id": "UChmxDh8nB90AYWDP9CTUd5Q",
      "author_thumbnail": "https://yt3.ggpht.com/ytc/AKedOLQNKhe1A87d8otNMhoeewLrnGojw_EcHG-eOg=s176-c-k-c0x00ffffff-no-rj",
      "author_is_uploader": false,
      "parent": "root"
    },
    {
      "id": "Ugxfmzv1ZuJ-QGgeQah4AaABAg",
      "text": "f*** this s*** I'm out no thinks",
      "timestamp": 1569542400,
      "time_text": "2 years ago",
      "like_count": 0,
      "is_favorited": false,
      "author": "Pokémon evee",
      "author_id": "UCYCtLytVh2hLEdAdC6mnSbQ",
      "author_thumbnail": "https://yt3.ggpht.com/ytc/AKedOLRfRdcmJk1eTByZiHrb6oujL1ozLhbCO_9i1VB4=s176-c-k-c0x00ffffff-no-rj",
      "author_is_uploader": false,
      "parent": "root"
    },
    {
      "id": "UgyT19dO2ndK6nhjKdh4AaABAg",
      "text": "=~=",
      "timestamp": 1569542400,
      "time_text": "2 years ago",
      "like_count": 1,
      "is_favorited": false,
      "author": "Pokémon evee",
      "author_id": "UCYCtLytVh2hLEdAdC6mnSbQ",
      "author_thumbnail": "https://yt3.ggpht.com/ytc/AKedOLRfRdcmJk1eTByZiHrb6oujL1ozLhbCO_9i1VB4=s176-c-k-c0x00ffffff-no-rj",
      "author_is_uploader": false,
      "parent": "root"
    },
    {
      "id": "UgwoVND6kLg4tpOjmvN4AaABAg",
      "text": "Wa",
      "timestamp": 1569542400,
      "time_text": "2 years ago",
      "like_count": 2,
      "is_favorited": false,
      "author": "Pokémon evee",
      "author_id": "UCYCtLytVh2hLEdAdC6mnSbQ",
      "author_thumbnail": "https://yt3.ggpht.com/ytc/AKedOLRfRdcmJk1eTByZiHrb6oujL1ozLhbCO_9i1VB4=s176-c-k-c0x00ffffff-no-rj",
      "author_is_uploader": false,
      "parent": "root"
    },
    {
      "id": "UgzuUwNL34ne5FTMXBZ4AaABAg",
      "text": "Not sure how I came across this glorious shit, but i'm sure glad I did! Tamers12345, you sir are the reincarnation of Jesus Christ himself.",
      "timestamp": 1569542400,
      "time_text": "2 years ago",
      "like_count": 4,
      "is_favorited": false,
      "author": "MortifiedAlias",
      "author_id": "UCMR2_H1Wj-gyRsuZZNDOLmw",
      "author_thumbnail": "https://yt3.ggpht.com/ytc/AKedOLTwNXtYuAiVxCyn1ijui9s_CWYF_erV1VEGzHdD=s176-c-k-c0x00ffffff-no-rj",
      "author_is_uploader": false,
      "parent": "root"
    },
    {
      "id": "UgzRZnxR6OKBbfa5zbR4AaABAg",
      "text": "Listen, I know all the comments on this video are fake praise. I know that. But this one went too far. WAY too far. I'd like to ask you something, Tamers. Are you okay? Is the pure physical and emotional torture that Mindy goes through some strange way for you to cope? Because it's sick. This video is sick, and makes mine and many others skin crawl. This isn't...normal. Even for a troll to create. I usually appreciate your animation and laugh at your videos like everyone else, but not this time. This is vile.",
      "timestamp": 1569542400,
      "time_text": "2 years ago",
      "like_count": 14,
      "is_favorited": false,
      "author": "Mocha",
      "author_id": "UCCjlCXQjKI0zJxyvTHcIJiw",
      "author_thumbnail": "https://yt3.ggpht.com/ytc/AKedOLQCVk8WfffV0E58VUXfG5alr2I9q_rbqQ_zEaVv=s176-c-k-c0x00ffffff-no-rj",
      "author_is_uploader": false,
      "parent": "root",
      "replies": [
        {
          "id": "UgzRZnxR6OKBbfa5zbR4AaABAg.8mzTmmLT8YL8oIuqzlOup3",
          "text": "fake praise?",
          "timestamp": 1569542400,
          "time_text": "2 years ago",
          "like_count": 11,
          "is_favorited": false,
          "author": "Badtooth",
          "author_id": "UCJFuKVy3oL-W9MVWEX0sG_Q",
          "author_thumbnail": "https://yt3.ggpht.com/ytc/AKedOLTjIkv9s0h0oBimyA0c5j0Y19POK4dZxA899yOb=s176-c-k-c0x00ffffff-no-rj",
          "author_is_uploader": false,
          "parent": "UgzRZnxR6OKBbfa5zbR4AaABAg"
        },
        {
          "id": "UgzRZnxR6OKBbfa5zbR4AaABAg.8mzTmmLT8YL8ovZ97F3p1k",
          "text": "I assure you nothing about our praise is fake",
          "timestamp": 1569542400,
          "time_text": "2 years ago",
          "like_count": 19,
          "is_favorited": false,
          "author": "Raye",
          "author_id": "UCJF-Kcz_LM6fvni217rUVFA",
          "author_thumbnail": "https://yt3.ggpht.com/ytc/AKedOLRS4nyvDYyWippSuUHv3OriC0j0d9VsnUbXpDeSKg=s176-c-k-c0x00ffffff-no-rj",
          "author_is_uploader": false,
          "parent": "UgzRZnxR6OKBbfa5zbR4AaABAg"
        },
        {
          "id": "UgzRZnxR6OKBbfa5zbR4AaABAg.8mzTmmLT8YL8p0cSFp373C",
          "text": " @Raye  lol ok sure, if that's really true, I can totally get that from the art aspect, bc Tamers has improved so much from when I first saw him. And he can be very very funny! Just not like this. I can usually laugh and appreciate his content, so I guess I revoke what I said about fake praise. It's just that these...\"jokes\"? Child abuse, rape, pedophile clowns? That stuff is not funny. And it's not that I don't think it's funny bc I'm sensitive. I'm really not sensitive, y'all. It just doesn't tickle my funny bone. When that stuff happens every day and is normalized through \"jokes\" like that, I can't see how they could ever be used as effective humor.  I don't like watching anything that exploits those things.",
          "timestamp": 1569542400,
          "time_text": "2 years ago",
          "like_count": 2,
          "is_favorited": false,
          "author": "Mocha",
          "author_id": "UCCjlCXQjKI0zJxyvTHcIJiw",
          "author_thumbnail": "https://yt3.ggpht.com/ytc/AKedOLQCVk8WfffV0E58VUXfG5alr2I9q_rbqQ_zEaVv=s176-c-k-c0x00ffffff-no-rj",
          "author_is_uploader": false,
          "parent": "UgzRZnxR6OKBbfa5zbR4AaABAg"
        },
        {
          "id": "UgzRZnxR6OKBbfa5zbR4AaABAg.8mzTmmLT8YL8pj7z8nFGDK",
          "text": " @Mocha  can u not. theres them making fun of black people and bartleby clawing and raping sonic in his previous works, but when its mindys life thats the butt of the joke then thats what sets you off? lol You seem to not realize why people make jokes in the first place. EDIT: Heres a bunch of veterans poking fun at their own experiences and other shit: https://youtu.be/yTrNxi3Uclw learn not to be a pussy",
          "timestamp": 1569542400,
          "time_text": "2 years ago (edited)",
          "like_count": 14,
          "is_favorited": false,
          "author": "†",
          "author_id": "UCtCkEpW3Zg9vnMJCNbt-b1A",
          "author_thumbnail": "https://yt3.ggpht.com/ytc/AKedOLTxWd4xE6HJuY5U8DbjFBYL8b7FnAKAlZW0E8GvHw=s176-c-k-c0x00ffffff-no-rj",
          "author_is_uploader": false,
          "parent": "UgzRZnxR6OKBbfa5zbR4AaABAg"
        },
        {
          "id": "UgzRZnxR6OKBbfa5zbR4AaABAg.8mzTmmLT8YL8pj8z-zSYY1",
          "text": " @Mocha  actually those things are very funny and you are incredibly sensitive",
          "timestamp": 1569542400,
          "time_text": "2 years ago",
          "like_count": 6,
          "is_favorited": false,
          "author": "Raye",
          "author_id": "UCJF-Kcz_LM6fvni217rUVFA",
          "author_thumbnail": "https://yt3.ggpht.com/ytc/AKedOLRS4nyvDYyWippSuUHv3OriC0j0d9VsnUbXpDeSKg=s176-c-k-c0x00ffffff-no-rj",
          "author_is_uploader": false,
          "parent": "UgzRZnxR6OKBbfa5zbR4AaABAg"
        },
        {
          "id": "UgzRZnxR6OKBbfa5zbR4AaABAg.8mzTmmLT8YL8pjMFl-WXJa",
          "text": " @†  preach dude, I dont want tamers to stop ever, he's so entertaining.",
          "timestamp": 1569542400,
          "time_text": "2 years ago",
          "like_count": 5,
          "is_favorited": false,
          "author": "Raye",
          "author_id": "UCJF-Kcz_LM6fvni217rUVFA",
          "author_thumbnail": "https://yt3.ggpht.com/ytc/AKedOLRS4nyvDYyWippSuUHv3OriC0j0d9VsnUbXpDeSKg=s176-c-k-c0x00ffffff-no-rj",
          "author_is_uploader": false,
          "parent": "UgzRZnxR6OKBbfa5zbR4AaABAg"
        },
        {
          "id": "UgzRZnxR6OKBbfa5zbR4AaABAg.8mzTmmLT8YL99fe_4vkHEJ",
          "text": "\"This isn't normal. Even for a troll to create\"\n\nIf you think this is bad, then clearly you haven't seen enough work by trolls",
          "timestamp": 1601164800,
          "time_text": "1 year ago",
          "like_count": 4,
          "is_favorited": false,
          "author": "Ale Titan",
          "author_id": "UC-eH6kZzhIq9uAC4FiLlL8w",
          "author_thumbnail": "https://yt3.ggpht.com/ytc/AKedOLRuEEjHg_SvmNmmt4ZOUnzx6Ntzohr3e_DNk7puTw=s176-c-k-c0x00ffffff-no-rj",
          "author_is_uploader": false,
          "parent": "UgzRZnxR6OKBbfa5zbR4AaABAg"
        },
        {
          "id": "UgzRZnxR6OKBbfa5zbR4AaABAg.8mzTmmLT8YL9R316ToN1AE",
          "text": "I hope all these years later you've grown up and realized how ignorant you are. Silly Mocha.",
          "timestamp": 1630022400,
          "time_text": "1 month ago",
          "like_count": 0,
          "is_favorited": false,
          "author": "Syracuse",
          "author_id": "UCuEWiDuXSVsX3xN2PDc3EYQ",
          "author_thumbnail": "https://yt3.ggpht.com/ytc/AKedOLTonpMNRp-Z_ve4SP5AuNuTrdW-WBz4BG763EwE1A=s176-c-k-c0x00ffffff-no-rj",
          "author_is_uploader": false,
          "parent": "UgzRZnxR6OKBbfa5zbR4AaABAg"
        }
      ]
    },
    {
      "id": "UgyDeCiU7vymdqHjLFt4AaABAg",
      "text": "Tamers you put sonic 2 times in the cast instead of sonia just letting you know",
      "timestamp": 1538006400,
      "time_text": "3 years ago",
      "like_count": 3,
      "is_favorited": false,
      "author": "the pony army",
      "author_id": "UCu5FcRRL-VCAKhqe74uPmQw",
      "author_thumbnail": "https://yt3.ggpht.com/ytc/AKedOLQjwLFn4er70TRaa-O8f_8kzDx0NJiQ6lYGz59T=s176-c-k-c0x00ffffff-no-rj",
      "author_is_uploader": false,
      "parent": "root"
    },
    {
      "id": "UgzrY9RnUzmTsMR-CdN4AaABAg",
      "text": "I've just found this and never leaving",
      "timestamp": 1538006400,
      "time_text": "3 years ago",
      "like_count": 2,
      "is_favorited": false,
      "author": "Jack",
      "author_id": "UCA8bwAFIw_AzTHA0ytjwkzg",
      "author_thumbnail": "https://yt3.ggpht.com/ytc/AKedOLTzHqxOJz-27AgBiGiu3ZKh9mEwXspsH1a3TQLFiw=s176-c-k-c0x00ffffff-no-rj",
      "author_is_uploader": false,
      "parent": "root"
    },
    {
      "id": "Ugzo9atOITiBj2HvzMF4AaABAg",
      "text": "Also can we please get a looping gif of bartleby dancing",
      "timestamp": 1538006400,
      "time_text": "3 years ago",
      "like_count": 13,
      "is_favorited": false,
      "author": "Raye",
      "author_id": "UCJF-Kcz_LM6fvni217rUVFA",
      "author_thumbnail": "https://yt3.ggpht.com/ytc/AKedOLRS4nyvDYyWippSuUHv3OriC0j0d9VsnUbXpDeSKg=s176-c-k-c0x00ffffff-no-rj",
      "author_is_uploader": false,
      "parent": "root"
    },
    {
      "id": "UgxBr9m8ZSITaIKow5R4AaABAg",
      "text": "\"my favorite part was when you stuck both of your clown shoes up my ass\"\n\nHoly fuck tamers youre amazing",
      "timestamp": 1538006400,
      "time_text": "3 years ago",
      "like_count": 3,
      "is_favorited": false,
      "author": "Raye",
      "author_id": "UCJF-Kcz_LM6fvni217rUVFA",
      "author_thumbnail": "https://yt3.ggpht.com/ytc/AKedOLRS4nyvDYyWippSuUHv3OriC0j0d9VsnUbXpDeSKg=s176-c-k-c0x00ffffff-no-rj",
      "author_is_uploader": false,
      "parent": "root"
    },
    {
      "id": "UgwL5raE2QunTinNZBV4AaABAg",
      "text": "I want a dvd or blu-ray with all of these movies.",
      "timestamp": 1538006400,
      "time_text": "3 years ago",
      "like_count": 20,
      "is_favorited": false,
      "author": "Sin V",
      "author_id": "UCxNfVHpZ46fem2ZQFNSHTyw",
      "author_thumbnail": "https://yt3.ggpht.com/ytc/AKedOLTcfiDH8bKKLUGS6SrOxhqcNOdcLRCCmPeRJPcigA=s176-c-k-c0x00ffffff-no-rj",
      "author_is_uploader": false,
      "parent": "root"
    },
    {
      "id": "Ugx7tbHrpFTzKs5hkmR4AaABAg",
      "text": "Mindy’s dad is hot",
      "timestamp": 1538006400,
      "time_text": "3 years ago",
      "like_count": 39,
      "is_favorited": false,
      "author": "CartoonWarStudios",
      "author_id": "UCMiWt1kGBTuO846ZeoSVMXQ",
      "author_thumbnail": "https://yt3.ggpht.com/ytc/AKedOLSbmHjTFzIa4rvZC7nNNH2QbYfOhTtkvtKDPVX-=s176-c-k-c0x00ffffff-no-rj",
      "author_is_uploader": false,
      "parent": "root",
      "replies": [
        {
          "id": "Ugx7tbHrpFTzKs5hkmR4AaABAg.8jw3KMxpYYb9KfLF6aNsn7",
          "text": "I know",
          "timestamp": 1616803200,
          "time_text": "6 months ago",
          "like_count": 0,
          "is_favorited": false,
          "author": "the ultimate Tamers one two three four five fan",
          "author_id": "UCv9kzw7j04IKQREAlk4614g",
          "author_thumbnail": "https://yt3.ggpht.com/ytc/AKedOLRG--Wmlyoj903bvXrVnP28AHyKYDSTgrGuLELw=s176-c-k-c0x00ffffff-no-rj",
          "author_is_uploader": false,
          "parent": "Ugx7tbHrpFTzKs5hkmR4AaABAg"
        }
      ]
    },
    {
      "id": "UgyFA1eeeZMmM3NsdjR4AaABAg",
      "text": "DRAKE NEJDNEJDJDHHD KM SO PROUD",
      "timestamp": 1538006400,
      "time_text": "3 years ago",
      "like_count": 1,
      "is_favorited": false,
      "author": "YipOhCo",
      "author_id": "UCNxtAiq9n0GhQe8X9GpfKXA",
      "author_thumbnail": "https://yt3.ggpht.com/ytc/AKedOLRwbg6sZCgmlcObXm8uD8__o858iW8f9IBKc77e9Q=s176-c-k-c0x00ffffff-no-rj",
      "author_is_uploader": false,
      "parent": "root"
    },
    {
      "id": "Ugzmh6qmLTkzZLuv4Nl4AaABAg",
      "text": "Whoops I almost said too much",
      "timestamp": 1538006400,
      "time_text": "3 years ago",
      "like_count": 5,
      "is_favorited": false,
      "author": "MeinCouch123",
      "author_id": "UChfQ7EL0_JDR-LDe6-sfLAw",
      "author_thumbnail": "https://yt3.ggpht.com/ytc/AKedOLTMYgOMiHsoLIhuAkezLHSpWmZh8T-Y8s_R83Bz=s176-c-k-c0x00ffffff-no-rj",
      "author_is_uploader": false,
      "parent": "root"
    },
    {
      "id": "UgyvqK275TCtulMWKCp4AaABAg",
      "text": "I turned on my notifications, your content just keeps getting better and better.",
      "timestamp": 1538006400,
      "time_text": "3 years ago",
      "like_count": 0,
      "is_favorited": false,
      "author": "Slurpwis",
      "author_id": "UCLANyFVDQk1_SOPXQ2krbcg",
      "author_thumbnail": "https://yt3.ggpht.com/ytc/AKedOLQ9w2gmiuYP28Pgic8VfQNUhakpQ0ZnBBC9ZNSR=s176-c-k-c0x00ffffff-no-rj",
      "author_is_uploader": false,
      "parent": "root"
    },
    {
      "id": "UgxEQszSNOZil-JuPO14AaABAg",
      "text": "Tamers, are you okay? This seems slightly off from your usual production. I can't quite place my finger on it, but it feels different. Please let me know if everything is okay.",
      "timestamp": 1538006400,
      "time_text": "3 years ago",
      "like_count": 14,
      "is_favorited": false,
      "author": "Michael Misfeldt",
      "author_id": "UCf9Q6SaDNfL90czHcOKaTUg",
      "author_thumbnail": "https://yt3.ggpht.com/ytc/AKedOLQa0NYDWNsb_7be75WFMuYySPkyUoYOLt-FPXA8=s176-c-k-c0x00ffffff-no-rj",
      "author_is_uploader": false,
      "parent": "root"
    },
    {
      "id": "UgxDPOfU7IP4Bm9Fg_J4AaABAg",
      "text": "1:16 \"It seems like just yesterday I was holding you as a baby. Now your boobs are the size of watermelons\"",
      "timestamp": 1538006400,
      "time_text": "3 years ago (edited)",
      "like_count": 1,
      "is_favorited": false,
      "author": "Ale Titan",
      "author_id": "UC-eH6kZzhIq9uAC4FiLlL8w",
      "author_thumbnail": "https://yt3.ggpht.com/ytc/AKedOLRuEEjHg_SvmNmmt4ZOUnzx6Ntzohr3e_DNk7puTw=s176-c-k-c0x00ffffff-no-rj",
      "author_is_uploader": false,
      "parent": "root"
    },
    {
      "id": "Ugyv6nyuJNBTunNaSV14AaABAg",
      "text": "this is so touching",
      "timestamp": 1538006400,
      "time_text": "3 years ago",
      "like_count": 3,
      "is_favorited": false,
      "author": "ice bear",
      "author_id": "UC5oo0rpu_ty0bD4CGvTpLFA",
      "author_thumbnail": "https://yt3.ggpht.com/ytc/AKedOLRJKmDngoEYKDkdQMNTmtgey38By8BXKi8xkOAD=s176-c-k-c0x00ffffff-no-rj",
      "author_is_uploader": false,
      "parent": "root"
    },
    {
      "id": "UgwISmB76VQYVSbaUGN4AaABAg",
      "text": "Im scared",
      "timestamp": 1538006400,
      "time_text": "3 years ago",
      "like_count": 0,
      "is_favorited": false,
      "author": "Oddy",
      "author_id": "UCx2Khn_REiVEC3OHO1sb6qQ",
      "author_thumbnail": "https://yt3.ggpht.com/ytc/AKedOLSClfcxxagvE77MTEKF6-qYsPIfHewQLCS3ff4Wkw=s176-c-k-c0x00ffffff-no-rj",
      "author_is_uploader": false,
      "parent": "root"
    },
    {
      "id": "UgwojIycPoIY94ogPIR4AaABAg",
      "text": "Please never stop making content, it's too good",
      "timestamp": 1538006400,
      "time_text": "3 years ago",
      "like_count": 6,
      "is_favorited": false,
      "author": "Walta",
      "author_id": "UCrSv6dLSWS9t9Ykcii-ZZ0A",
      "author_thumbnail": "https://yt3.ggpht.com/ytc/AKedOLTfhDM33P0D-3WLWxo2dJcWg6DDHSTvp_SH2mww=s176-c-k-c0x00ffffff-no-rj",
      "author_is_uploader": false,
      "parent": "root"
    },
    {
      "id": "UgxlsjWm-AHrU6ilRJ54AaABAg",
      "text": "Bartleby was looking a little lanky this episode Tamers. I’m disappointed, I need to see more of his thick bara bod",
      "timestamp": 1538006400,
      "time_text": "3 years ago",
      "like_count": 61,
      "is_favorited": false,
      "author": "Anonymous Alias",
      "author_id": "UC5EEvmiB_YLr7vl2ZAEZlYA",
      "author_thumbnail": "https://yt3.ggpht.com/ytc/AKedOLRZ67HEndF47ZTw5rL7UdXiZdqT9kTp-vG8x5vR=s176-c-k-c0x00ffffff-no-rj",
      "author_is_uploader": false,
      "parent": "root",
      "replies": [
        {
          "id": "UgxlsjWm-AHrU6ilRJ54AaABAg.8jnrwZ1tIRG9KfL7Aghnkh",
          "text": "Fuck you",
          "timestamp": 1616803200,
          "time_text": "6 months ago",
          "like_count": 4,
          "is_favorited": false,
          "author": "the ultimate Tamers one two three four five fan",
          "author_id": "UCv9kzw7j04IKQREAlk4614g",
          "author_thumbnail": "https://yt3.ggpht.com/ytc/AKedOLRG--Wmlyoj903bvXrVnP28AHyKYDSTgrGuLELw=s176-c-k-c0x00ffffff-no-rj",
          "author_is_uploader": false,
          "parent": "UgxlsjWm-AHrU6ilRJ54AaABAg"
        },
        {
          "id": "UgxlsjWm-AHrU6ilRJ54AaABAg.8jnrwZ1tIRG9KfLBh_CMBC",
          "text": "Tamers  Art is amazing you are a monster",
          "timestamp": 1616803200,
          "time_text": "6 months ago",
          "like_count": 4,
          "is_favorited": false,
          "author": "the ultimate Tamers one two three four five fan",
          "author_id": "UCv9kzw7j04IKQREAlk4614g",
          "author_thumbnail": "https://yt3.ggpht.com/ytc/AKedOLRG--Wmlyoj903bvXrVnP28AHyKYDSTgrGuLELw=s176-c-k-c0x00ffffff-no-rj",
          "author_is_uploader": false,
          "parent": "UgxlsjWm-AHrU6ilRJ54AaABAg"
        }
      ]
    },
    {
      "id": "UgybfXaVOkCpwr-O5oh4AaABAg",
      "text": "Wonderful work, Daddy Tamers. ^o^ Can't wait for the next video.",
      "timestamp": 1538006400,
      "time_text": "3 years ago",
      "like_count": 1,
      "is_favorited": false,
      "author": "Crystal",
      "author_id": "UCDux4PQZzeU1MkKupMPtN4w",
      "author_thumbnail": "https://yt3.ggpht.com/ytc/AKedOLS6DIgueChd0ZGqkAxuzHOJx2nmipGoe5mTGsx65A=s176-c-k-c0x00ffffff-no-rj",
      "author_is_uploader": false,
      "parent": "root"
    },
    {
      "id": "Ugx1hMbnl11N6R9KCEJ4AaABAg",
      "text": "Me at 5 am:",
      "timestamp": 1538006400,
      "time_text": "3 years ago",
      "like_count": 0,
      "is_favorited": false,
      "author": "Gray_FoxRJ",
      "author_id": "UCMJHK58DgYdyJ50VOANvTIg",
      "author_thumbnail": "https://yt3.ggpht.com/yU3IUaiYBDqshu9T1_BS2gB68i5nU1WwHfbiXFRJszEEKlzFxJUpL9cHmd0Kjh1zaq1JPNi-vCM=s176-c-k-c0x00ffffff-no-rj",
      "author_is_uploader": false,
      "parent": "root"
    },
    {
      "id": "UgwTnhN_a2jyAHNcP8t4AaABAg",
      "text": "I'll be sure to get this video taken down. Disgusting.",
      "timestamp": 1538006400,
      "time_text": "3 years ago",
      "like_count": 4,
      "is_favorited": false,
      "author": "Memein' and Dreamin'",
      "author_id": "UCskbjd5l7JiU2mlutelfw9A",
      "author_thumbnail": "https://yt3.ggpht.com/ytc/AKedOLQKgipH-ydwJgdjndOkdMRfMrFkvlOfjHFTwtwB-g=s176-c-k-c0x00ffffff-no-rj",
      "author_is_uploader": false,
      "parent": "root",
      "replies": [
        {
          "id": "UgwTnhN_a2jyAHNcP8t4AaABAg.8jnPMxuQgID8jne-p5WOhS",
          "text": "Try me bitch. I've got enough subscribers and money form ad cents to buy your account.",
          "timestamp": 1538006400,
          "time_text": "3 years ago",
          "like_count": 58,
          "is_favorited": false,
          "author": "Tamers12345",
          "author_id": "UCQLVTT8LkgSOyZ2mD8BU3dA",
          "author_thumbnail": "https://yt3.ggpht.com/ytc/AKedOLQUcdfcbJEWtPW6qAwC1DgPcCOqZ6Z_8dBsA6xXCQ=s176-c-k-c0x00ffffff-no-rj",
          "author_is_uploader": true,
          "parent": "UgwTnhN_a2jyAHNcP8t4AaABAg"
        },
        {
          "id": "UgwTnhN_a2jyAHNcP8t4AaABAg.8jnPMxuQgID8jomcE2lg7X",
          "text": " @Tamers12345  Big talk coming from a furry.",
          "timestamp": 1538006400,
          "time_text": "3 years ago",
          "like_count": 1,
          "is_favorited": false,
          "author": "Memein' and Dreamin'",
          "author_id": "UCskbjd5l7JiU2mlutelfw9A",
          "author_thumbnail": "https://yt3.ggpht.com/ytc/AKedOLQKgipH-ydwJgdjndOkdMRfMrFkvlOfjHFTwtwB-g=s176-c-k-c0x00ffffff-no-rj",
          "author_is_uploader": false,
          "parent": "UgwTnhN_a2jyAHNcP8t4AaABAg"
        },
        {
          "id": "UgwTnhN_a2jyAHNcP8t4AaABAg.8jnPMxuQgID8k14dMqntwV",
          "text": "16-Bit Trev you cant talk to tamers that way wtf",
          "timestamp": 1538006400,
          "time_text": "3 years ago",
          "like_count": 15,
          "is_favorited": false,
          "author": "Raye",
          "author_id": "UCJF-Kcz_LM6fvni217rUVFA",
          "author_thumbnail": "https://yt3.ggpht.com/ytc/AKedOLRS4nyvDYyWippSuUHv3OriC0j0d9VsnUbXpDeSKg=s176-c-k-c0x00ffffff-no-rj",
          "author_is_uploader": false,
          "parent": "UgwTnhN_a2jyAHNcP8t4AaABAg"
        },
        {
          "id": "UgwTnhN_a2jyAHNcP8t4AaABAg.8jnPMxuQgID9Bi9rto8Kmz",
          "text": "Comments that aged poorly",
          "timestamp": 1601164800,
          "time_text": "1 year ago",
          "like_count": 5,
          "is_favorited": false,
          "author": "Sunny Rustles",
          "author_id": "UClOT2mkpY08mwCYyCipaCgQ",
          "author_thumbnail": "https://yt3.ggpht.com/ytc/AKedOLSFy5vh-0RvAzRAcDKUn5mdJQClUqj4JGDnm0pvEA=s176-c-k-c0x00ffffff-no-rj",
          "author_is_uploader": false,
          "parent": "UgwTnhN_a2jyAHNcP8t4AaABAg"
        },
        {
          "id": "UgwTnhN_a2jyAHNcP8t4AaABAg.8jnPMxuQgID9C9h8fMk5Zd",
          "text": " @Memein' and Dreamin'  don't talk to our Lord and savoir like that",
          "timestamp": 1601164800,
          "time_text": "1 year ago",
          "like_count": 2,
          "is_favorited": false,
          "author": "Son son the goddess of confusion",
          "author_id": "UCCFR4ON3OjBnX76CqQ5F5xA",
          "author_thumbnail": "https://yt3.ggpht.com/Emkj9lrX-XdKjLOq3Pnt-7Jt6elvhLq7vMiOiLiwdm_-F7pEV253msdhJ0P21lvchbRoKqQrqQw=s176-c-k-c0x00ffffff-no-rj",
          "author_is_uploader": false,
          "parent": "UgwTnhN_a2jyAHNcP8t4AaABAg"
        },
        {
          "id": "UgwTnhN_a2jyAHNcP8t4AaABAg.8jnPMxuQgID9PXJqAj_S_e",
          "text": "Powerless wails",
          "timestamp": 1627344000,
          "time_text": "2 months ago",
          "like_count": 0,
          "is_favorited": false,
          "author": "Hou",
          "author_id": "UCipbFExJtfx31Shjh97fCsQ",
          "author_thumbnail": "https://yt3.ggpht.com/ytc/AKedOLQ6CfDWxoa5zCNT2T-5nTM32tVTJWinvotSP8siKg=s176-c-k-c0x00ffffff-no-rj",
          "author_is_uploader": false,
          "parent": "UgwTnhN_a2jyAHNcP8t4AaABAg"
        }
      ]
    },
    {
      "id": "UgyF6R8nGzv2j0oTqzR4AaABAg",
      "text": "How do you keep coming up with the best shit?  Every time I think \"damn, shit sucks, I wish tamers was back\" and then boom.  You pull this shit.  God damn.  Fucking Tamers12345 is the best god.  The God of sonic underground.",
      "timestamp": 1538006400,
      "time_text": "3 years ago",
      "like_count": 0,
      "is_favorited": false,
      "author": "Josh",
      "author_id": "UC9QubSe3gyr7-wqM-CwIzhw",
      "author_thumbnail": "https://yt3.ggpht.com/ytc/AKedOLROtqYMg346vGgu4w92mJx9r5kJj6SFJG8Fcg=s176-c-k-c0x00ffffff-no-rj",
      "author_is_uploader": false,
      "parent": "root"
    },
    {
      "id": "Ugwf5mBiNwiOtZSagKZ4AaABAg",
      "text": "Nobody else notices the Clannad music but me. Keep up the great work Tamers!",
      "timestamp": 1538006400,
      "time_text": "3 years ago",
      "like_count": 8,
      "is_favorited": false,
      "author": "HotSause",
      "author_id": "UC68C7Xr3BPhXZeOBSAarZ0g",
      "author_thumbnail": "https://yt3.ggpht.com/ytc/AKedOLR6UFL1ajCIj1epYSzznP4NKuGTeKWO9pl_ciqN=s176-c-k-c0x00ffffff-no-rj",
      "author_is_uploader": false,
      "parent": "root"
    },
    {
      "id": "Ugwnx9RfesQ30T2Ppqt4AaABAg",
      "text": "n..",
      "timestamp": 1538006400,
      "time_text": "3 years ago",
      "like_count": 2,
      "is_favorited": false,
      "author": "okgoogle",
      "author_id": "UCTLrdjrz--emINJ32KQ0jOg",
      "author_thumbnail": "https://yt3.ggpht.com/ytc/AKedOLRJmdWeEZ4nUgTKCbxWqOzyJGcHeMxB_Qvj2Cv5Xw=s176-c-k-c0x00ffffff-no-rj",
      "author_is_uploader": false,
      "parent": "root"
    },
    {
      "id": "Ugyc9j8KGlOR6W1hNKN4AaABAg",
      "text": "Tamers I owe you my life.",
      "timestamp": 1538006400,
      "time_text": "3 years ago",
      "like_count": 14,
      "is_favorited": false,
      "author": "Kitley",
      "author_id": "UCpdOLw4hoOGCslWbJqMO7bA",
      "author_thumbnail": "https://yt3.ggpht.com/ytc/AKedOLT3PHYsPvKnFu6kx7u7IdxS6TFwmIDgSeu3cpvKiQ=s176-c-k-c0x00ffffff-no-rj",
      "author_is_uploader": false,
      "parent": "root"
    },
    {
      "id": "UgzL_TbGxFqHZ8DP8ot4AaABAg",
      "text": "Name a single fucking content creator better than Tamers. You literally can't. Keeping Sonic Underground alive loud and proud.",
      "timestamp": 1538006400,
      "time_text": "3 years ago",
      "like_count": 66,
      "is_favorited": false,
      "author": "Pablo Acevedo",
      "author_id": "UCyVo_M7-k1IjIK_ZH5iWhWQ",
      "author_thumbnail": "https://yt3.ggpht.com/ytc/AKedOLTiq0fJw5zClOBXkYrMfKYQmAmVvTPeNwgiLf8Ukw=s176-c-k-c0x00ffffff-no-rj",
      "author_is_uploader": false,
      "parent": "root",
      "replies": [
        {
          "id": "UgzL_TbGxFqHZ8DP8ot4AaABAg.8jn8E_WMGbq8sTuZkW7-sp",
          "text": " @Tanya Garduno  Fuck off and go watch some shitty makeup tutorials or some shit, Tamer is literally the best thing to happen to this platform.",
          "timestamp": 1569542400,
          "time_text": "2 years ago",
          "like_count": 1,
          "is_favorited": false,
          "author": "El Diablo",
          "author_id": "UC4RV6E29gnfIKthF9xPhZhg",
          "author_thumbnail": "https://yt3.ggpht.com/ytc/AKedOLTIetmSuoANSrFVNcGxOa4jFsAjn5_FNIALYlv5=s176-c-k-c0x00ffffff-no-rj",
          "author_is_uploader": false,
          "parent": "UgzL_TbGxFqHZ8DP8ot4AaABAg"
        },
        {
          "id": "UgzL_TbGxFqHZ8DP8ot4AaABAg.8jn8E_WMGbq8sWLcZEr5FY",
          "text": " @El Diablo  tamer is literally the best and I just saw 2 videos 😂",
          "timestamp": 1569542400,
          "time_text": "2 years ago",
          "like_count": 0,
          "is_favorited": false,
          "author": "Subject28 X",
          "author_id": "UC7FIBILoKPA0cucAYwlizbw",
          "author_thumbnail": "https://yt3.ggpht.com/ytc/AKedOLQFj6J2adxR0PtvhwRatFyt8yjgmph5u6Jr16sKqA=s176-c-k-c0x00ffffff-no-rj",
          "author_is_uploader": false,
          "parent": "UgzL_TbGxFqHZ8DP8ot4AaABAg"
        },
        {
          "id": "UgzL_TbGxFqHZ8DP8ot4AaABAg.8jn8E_WMGbq8ssVUGaV3GU",
          "text": " @El Diablo  But tammer's videos are really weird",
          "timestamp": 1569542400,
          "time_text": "2 years ago",
          "like_count": 0,
          "is_favorited": false,
          "author": "J Lawal",
          "author_id": "UC6ph0e6oDc3itYiHTJvZCLw",
          "author_thumbnail": "https://yt3.ggpht.com/ks9sO__bjTPc2VDGWPHsGt9L8aSGPs8lFlj3gOK5ABVUfE3S_Mg_gA_7yj1aMfowlYXfyKsTdjM=s176-c-k-c0x00ffffff-no-rj",
          "author_is_uploader": false,
          "parent": "UgzL_TbGxFqHZ8DP8ot4AaABAg"
        }
      ]
    },
    {
      "id": "UgygndnedQKZmJ74tAR4AaABAg",
      "text": "whoops ha-ha",
      "timestamp": 1538006400,
      "time_text": "3 years ago",
      "like_count": 1,
      "is_favorited": false,
      "author": "EGG ATTACK",
      "author_id": "UCjRh63RJ6ybq9uS85nkbCuw",
      "author_thumbnail": "https://yt3.ggpht.com/ytc/AKedOLTxAw-EuNnlVF9puOMvPHbICKNblduxavpK2SOL5g=s176-c-k-c0x00ffffff-no-rj",
      "author_is_uploader": false,
      "parent": "root"
    },
    {
      "id": "Ugw5wrTNuDR53xLv31t4AaABAg",
      "text": "YOU DON'T KNOW WHERE HE'S BEEN!",
      "timestamp": 1538006400,
      "time_text": "3 years ago",
      "like_count": 49,
      "is_favorited": false,
      "author": "Makoto Ikari",
      "author_id": "UCA_mWYI3q9Aj5DygsIYu0iw",
      "author_thumbnail": "https://yt3.ggpht.com/ytc/AKedOLSbs8OU0TMM2scXljO0CeK5gJbLPRSD2gx9fCVtrw=s176-c-k-c0x00ffffff-no-rj",
      "author_is_uploader": false,
      "parent": "root"
    },
    {
      "id": "Ugxkc2RNnfnFYlkaveZ4AaABAg",
      "text": "Lol \"happy birthday Daniel\"",
      "timestamp": 1538006400,
      "time_text": "3 years ago",
      "like_count": 39,
      "is_favorited": false,
      "author": "Cameron Koontz",
      "author_id": "UCkLf06v1rrd7lK0BsmTmokg",
      "author_thumbnail": "https://yt3.ggpht.com/ytc/AKedOLS5BXm-XJxZZR81qf_hct4J_n5VH7n5Mp4r98jPXA=s176-c-k-c0x00ffffff-no-rj",
      "author_is_uploader": false,
      "parent": "root"
    },
    {
      "id": "Ugzq7iFFdd9p56kTDfZ4AaABAg",
      "text": "doesnt get much better than this sips on a monster",
      "timestamp": 1538006400,
      "time_text": "3 years ago",
      "like_count": 34,
      "is_favorited": false,
      "author": "kevin smith",
      "author_id": "UC6YJIU1uGP7_9uQUxEWB0Xg",
      "author_thumbnail": "https://yt3.ggpht.com/ytc/AKedOLTYiOArT1YlyO-SM_0uEGOvuqKPTbOenYEscMzthw=s176-c-k-c0x00ffffff-no-rj",
      "author_is_uploader": false,
      "parent": "root",
      "replies": [
        {
          "id": "Ugzq7iFFdd9p56kTDfZ4AaABAg.8jmzCenP8dv8lmjzoWx_Y2",
          "text": "yep, Sonic Underground was a good show",
          "timestamp": 1569542400,
          "time_text": "2 years ago",
          "like_count": 6,
          "is_favorited": false,
          "author": "Canas",
          "author_id": "UCYUYN88UOkRkpJqQMcEa-Eg",
          "author_thumbnail": "https://yt3.ggpht.com/ytc/AKedOLRSt6UtzRWrYoOC1w198TKVgWJemd-BrIUubL41Lg=s176-c-k-c0x00ffffff-no-rj",
          "author_is_uploader": false,
          "parent": "Ugzq7iFFdd9p56kTDfZ4AaABAg"
        }
      ]
    },
    {
      "id": "Ugyias5Z2MjsoVCmBtt4AaABAg",
      "text": "But who is Mindy's mother? Will it ever be revealed?",
      "timestamp": 1538006400,
      "time_text": "3 years ago",
      "like_count": 8,
      "is_favorited": false,
      "author": "Anthony Kolodziej",
      "author_id": "UC49_nfFvXcXnny0kUEl-WiQ",
      "author_thumbnail": "https://yt3.ggpht.com/ytc/AKedOLSUN0OPuqDSP4BGxJ0ViFwlGpQlXjz-5hsFSzPN40w=s176-c-k-c0x00ffffff-no-rj",
      "author_is_uploader": false,
      "parent": "root"
    },
    {
      "id": "UgxsiNiG0R68ZM_vw4Z4AaABAg",
      "text": "Amazing",
      "timestamp": 1538006400,
      "time_text": "3 years ago",
      "like_count": 0,
      "is_favorited": false,
      "author": "IKenSpelGud",
      "author_id": "UCafjbSuN4vGFRL454ci2rJQ",
      "author_thumbnail": "https://yt3.ggpht.com/ytc/AKedOLQKGOJ4RalgAgEyCZiTyBBmGBOeZ5bqG0quZQ=s176-c-k-c0x00ffffff-no-rj",
      "author_is_uploader": false,
      "parent": "root"
    },
    {
      "id": "UgwNk-wrZgRB25UIcjt4AaABAg",
      "text": "Happy Birthday Daniel.",
      "timestamp": 1538006400,
      "time_text": "3 years ago",
      "like_count": 2,
      "is_favorited": false,
      "author": "PhantomLola12",
      "author_id": "UCXH4zMsQgjPyLEuyqVP3McQ",
      "author_thumbnail": "https://yt3.ggpht.com/ytc/AKedOLTeVIY3g588XDDFScVkEhY4vhscYa60pQRlC9iM=s176-c-k-c0x00ffffff-no-rj",
      "author_is_uploader": false,
      "parent": "root"
    },
    {
      "id": "UgxQFh2wAafGwwJ95vB4AaABAg",
      "text": "Great vid, we could always use some more mindy in our lives.",
      "timestamp": 1538006400,
      "time_text": "3 years ago",
      "like_count": 5,
      "is_favorited": false,
      "author": "†",
      "author_id": "UCtCkEpW3Zg9vnMJCNbt-b1A",
      "author_thumbnail": "https://yt3.ggpht.com/ytc/AKedOLTxWd4xE6HJuY5U8DbjFBYL8b7FnAKAlZW0E8GvHw=s176-c-k-c0x00ffffff-no-rj",
      "author_is_uploader": false,
      "parent": "root"
    },
    {
      "id": "UgxMArP46ks9p4DRXv54AaABAg",
      "text": "another amazing story",
      "timestamp": 1538006400,
      "time_text": "3 years ago",
      "like_count": 1,
      "is_favorited": false,
      "author": "Stig Archives",
      "author_id": "UCfhqAaQ-0RfM_IaFM1Xp-ng",
      "author_thumbnail": "https://yt3.ggpht.com/ytc/AKedOLTTv-gdQh-wp6QC2PK_pIPu6LtTjJ92_XWjZ_Gb5A=s176-c-k-c0x00ffffff-no-rj",
      "author_is_uploader": false,
      "parent": "root"
    },
    {
      "id": "UgyUXeLjV-JTkXY4PGJ4AaABAg",
      "text": "Tamers,pls respond this is good!I can't believe this",
      "timestamp": 1538006400,
      "time_text": "3 years ago",
      "like_count": 2,
      "is_favorited": false,
      "author": "Nori",
      "author_id": "UClmnkcRNtW8ZW8XbgFm20Kg",
      "author_thumbnail": "https://yt3.ggpht.com/ytc/AKedOLTLfgV9VKRzmrb14gDUnV5Xsqg4hF2k2jwWcYKv9g=s176-c-k-c0x00ffffff-no-rj",
      "author_is_uploader": false,
      "parent": "root"
    },
    {
      "id": "UgzGpnNqj3tnJZhDEwB4AaABAg",
      "text": "FUCK YES I'VE WANTED THIS FOR SO LONG",
      "timestamp": 1538006400,
      "time_text": "3 years ago",
      "like_count": 0,
      "is_favorited": false,
      "author": "perhapsrenren",
      "author_id": "UCPaYhp9DEMG3DLOK-9lavoQ",
      "author_thumbnail": "https://yt3.ggpht.com/sPUPtXIShW6boUFnNzzK7mVTvWXTugwnAcvTw2qpCINTnft5247wL1YpdXeBnkR41ERT78s_-w=s176-c-k-c0x00ffffff-no-rj",
      "author_is_uploader": false,
      "parent": "root",
      "replies": [
        {
          "id": "UgzGpnNqj3tnJZhDEwB4AaABAg.8jmjwI7qshW8jmkhzgjLYM",
          "text": "Also, this episode is super sad :(",
          "timestamp": 1538006400,
          "time_text": "3 years ago",
          "like_count": 0,
          "is_favorited": false,
          "author": "perhapsrenren",
          "author_id": "UCPaYhp9DEMG3DLOK-9lavoQ",
          "author_thumbnail": "https://yt3.ggpht.com/sPUPtXIShW6boUFnNzzK7mVTvWXTugwnAcvTw2qpCINTnft5247wL1YpdXeBnkR41ERT78s_-w=s176-c-k-c0x00ffffff-no-rj",
          "author_is_uploader": false,
          "parent": "UgzGpnNqj3tnJZhDEwB4AaABAg"
        }
      ]
    },
    {
      "id": "UgwpvGK9KoZUn2sahDF4AaABAg",
      "text": "Tamers you're a genius, this shit gets better every upload.",
      "timestamp": 1538006400,
      "time_text": "3 years ago",
      "like_count": 50,
      "is_favorited": false,
      "author": "Cloudscape",
      "author_id": "UC8zZVcxcnh_8B0hgxFI2rOQ",
      "author_thumbnail": "https://yt3.ggpht.com/ytc/AKedOLRlPm-DHZwp1dvvnID7sNr5r6Vb6LKDkaNotYcf=s176-c-k-c0x00ffffff-no-rj",
      "author_is_uploader": false,
      "parent": "root",
      "replies": [
        {
          "id": "UgwpvGK9KoZUn2sahDF4AaABAg.8jmjqYhw2Bm8jne1ex0LjQ",
          "text": "I know. Only the best for my channel",
          "timestamp": 1538006400,
          "time_text": "3 years ago",
          "like_count": 32,
          "is_favorited": false,
          "author": "Tamers12345",
          "author_id": "UCQLVTT8LkgSOyZ2mD8BU3dA",
          "author_thumbnail": "https://yt3.ggpht.com/ytc/AKedOLQUcdfcbJEWtPW6qAwC1DgPcCOqZ6Z_8dBsA6xXCQ=s176-c-k-c0x00ffffff-no-rj",
          "author_is_uploader": true,
          "parent": "UgwpvGK9KoZUn2sahDF4AaABAg"
        },
        {
          "id": "UgwpvGK9KoZUn2sahDF4AaABAg.8jmjqYhw2Bm9KkhwhIA9-G",
          "text": " @Tamers12345  you are the best",
          "timestamp": 1616803200,
          "time_text": "6 months ago",
          "like_count": 1,
          "is_favorited": false,
          "author": "the ultimate Tamers one two three four five fan",
          "author_id": "UCv9kzw7j04IKQREAlk4614g",
          "author_thumbnail": "https://yt3.ggpht.com/ytc/AKedOLRG--Wmlyoj903bvXrVnP28AHyKYDSTgrGuLELw=s176-c-k-c0x00ffffff-no-rj",
          "author_is_uploader": false,
          "parent": "UgwpvGK9KoZUn2sahDF4AaABAg"
        }
      ]
    },
    {
      "id": "UgzFDiqfuA1sPs-UNuJ4AaABAg",
      "text": "Tamers, you draw ass like a god",
      "timestamp": 1538006400,
      "time_text": "3 years ago",
      "like_count": 6,
      "is_favorited": false,
      "author": "ᅚ﻿ᅚ﻿ᅚ﻿ᅚ﻿",
      "author_id": "UC2NJyJUKQWwJkgzzCUx1iZw",
      "author_thumbnail": "https://yt3.ggpht.com/ytc/AKedOLT151FJBYJt3JNfD0PNRq41HGOLOapI_rjnI8HGTA=s176-c-k-c0x00ffffff-no-rj",
      "author_is_uploader": false,
      "parent": "root"
    },
    {
      "id": "Ugxb9ixybKZG0wTAfE14AaABAg",
      "text": "Mindy! My favorite character! I was wondering when she would be back, this is a blessing! Thank you daddy!",
      "timestamp": 1538006400,
      "time_text": "3 years ago",
      "like_count": 21,
      "is_favorited": false,
      "author": "Sookaretto",
      "author_id": "UCLJy3erbT16Qi5ijPr0fXsw",
      "author_thumbnail": "https://yt3.ggpht.com/ytc/AKedOLSiy9gVLUL6OIQAcRUUshnXGByDopzM7oLkHPtDZxU=s176-c-k-c0x00ffffff-no-rj",
      "author_is_uploader": false,
      "parent": "root"
    }
  ],
  "comment_count": 93,
  "epoch": 1632667604
}